Workbook
Name UPDATE: HCLTech!$E$1
Name UPDATE: Infosys!$E$1
Name UPDATE: TCS!$E$1
Name UPDATE: TechM!$E$1
Name UPDATE: Wipro!$E$1
Name UPDATE: #REF!

Sheet Summary
A1: Company | B1: Year | C1: Revenue | D1: Net Profit | E1: Total Assets | F1: Equity Capital | G1: Reserves | H1: Shareholders' Equity | I1: Borrowings | J1: EPS | K1: ROE | L1: ROCE
A2: TCS | B2: 42825 | C2: =INDEX(TCS!$B:$K,MATCH("Sales",TCS!$A:$A,0),MATCH($B2,TCS!$B$16:$K$16,0)) -> 117966 | D2: =INDEX(TCS!$B:$K,MATCH("Net profit",TCS!$A:$A,0),MATCH($B2,TCS!$B$16:$K$16,0)) -> 26289 | E2: =TCS!B66 -> 102333 | F2: =INDEX(TCS!$B:$K,MATCH("Equity Share Capital",TCS!$A:$A,0),MATCH($B2,TCS!$B$16:$K$16,0)) -> 197 | G2: =INDEX(TCS!$B:$K,MATCH("Reserves",TCS!$A:$A,0),MATCH($B2,TCS!$B$16:$K$16,0)) -> 86017 | H2: =F2+G2 -> 86214 | I2: =INDEX(TCS!$B:$K,MATCH("Borrowings",TCS!$A:$A,0),MATCH($B2,TCS!$B$16:$K$16,0)) -> 289 | J2: =INDEX(TCS!$B:$K,MATCH("EPS",TCS!$A:$A,0),MATCH($B2,TCS!$B$16:$K$16,0)) -> 66.708112 | K2: =INDEX(TCS!$B:$K,MATCH("Return on Equity",TCS!$A:$A,0),MATCH($B2,TCS!$B$16:$K$16,0)) -> 0.30492727
A3: TCS | B3: 43190 | C3: =INDEX(TCS!$B:$K,MATCH("Sales",TCS!$A:$A,0),MATCH($B3,TCS!$B$16:$K$16,0)) -> 123104 | D3: =INDEX(TCS!$B:$K,MATCH("Net profit",TCS!$A:$A,0),MATCH($B3,TCS!$B$16:$K$16,0)) -> 25826 | E3: =TCS!C66 -> 105126 | F3: =INDEX(TCS!$B:$K,MATCH("Equity Share Capital",TCS!$A:$A,0),MATCH($B3,TCS!$B$16:$K$16,0)) -> 191 | G3: =INDEX(TCS!$B:$K,MATCH("Reserves",TCS!$A:$A,0),MATCH($B3,TCS!$B$16:$K$16,0)) -> 84937 | H3: =F3+G3 -> 85128 | I3: =INDEX(TCS!$B:$K,MATCH("Borrowings",TCS!$A:$A,0),MATCH($B3,TCS!$B$16:$K$16,0)) -> 247 | J3: =INDEX(TCS!$B:$K,MATCH("EPS",TCS!$A:$A,0),MATCH($B3,TCS!$B$16:$K$16,0)) -> 67.455467 | K3: =INDEX(TCS!$B:$K,MATCH("Return on Equity",TCS!$A:$A,0),MATCH($B3,TCS!$B$16:$K$16,0)) -> 0.30337844 | L3: =INDEX(TCS!$B:$K,MATCH("Return on Capital Emp",TCS!$A:$A,0),MATCH($B3,TCS!$B$16:$K$16,0)) -> 0.39730507
A4: TCS | B4: 43555 | C4: =INDEX(TCS!$B:$K,MATCH("Sales",TCS!$A:$A,0),MATCH($B4,TCS!$B$16:$K$16,0)) -> 146463 | D4: =INDEX(TCS!$B:$K,MATCH("Net profit",TCS!$A:$A,0),MATCH($B4,TCS!$B$16:$K$16,0)) -> 31472 | E4: =TCS!D66 -> 113901 | F4: =INDEX(TCS!$B:$K,MATCH("Equity Share Capital",TCS!$A:$A,0),MATCH($B4,TCS!$B$16:$K$16,0)) -> 375 | G4: =INDEX(TCS!$B:$K,MATCH("Reserves",TCS!$A:$A,0),MATCH($B4,TCS!$B$16:$K$16,0)) -> 89071 | H4: =F4+G4 -> 89446 | I4: =INDEX(TCS!$B:$K,MATCH("Borrowings",TCS!$A:$A,0),MATCH($B4,TCS!$B$16:$K$16,0)) -> 62 | J4: =INDEX(TCS!$B:$K,MATCH("EPS",TCS!$A:$A,0),MATCH($B4,TCS!$B$16:$K$16,0)) -> 83.871655 | K4: =INDEX(TCS!$B:$K,MATCH("Return on Equity",TCS!$A:$A,0),MATCH($B4,TCS!$B$16:$K$16,0)) -> 0.35185475 | L4: =INDEX(TCS!$B:$K,MATCH("Return on Capital Emp",TCS!$A:$A,0),MATCH($B4,TCS!$B$16:$K$16,0)) -> 0.47758787
A5: TCS | B5: 43921 | C5: =INDEX(TCS!$B:$K,MATCH("Sales",TCS!$A:$A,0),MATCH($B5,TCS!$B$16:$K$16,0)) -> 156949 | D5: =INDEX(TCS!$B:$K,MATCH("Net profit",TCS!$A:$A,0),MATCH($B5,TCS!$B$16:$K$16,0)) -> 32340 | E5: =TCS!E66 -> 120127 | F5: =INDEX(TCS!$B:$K,MATCH("Equity Share Capital",TCS!$A:$A,0),MATCH($B5,TCS!$B$16:$K$16,0)) -> 375 | G5: =INDEX(TCS!$B:$K,MATCH("Reserves",TCS!$A:$A,0),MATCH($B5,TCS!$B$16:$K$16,0)) -> 83751 | H5: =F5+G5 -> 84126 | I5: =INDEX(TCS!$B:$K,MATCH("Borrowings",TCS!$A:$A,0),MATCH($B5,TCS!$B$16:$K$16,0)) -> 8174 | J5: =INDEX(TCS!$B:$K,MATCH("EPS",TCS!$A:$A,0),MATCH($B5,TCS!$B$16:$K$16,0)) -> 86.184842 | K5: =INDEX(TCS!$B:$K,MATCH("Return on Equity",TCS!$A:$A,0),MATCH($B5,TCS!$B$16:$K$16,0)) -> 0.38442336 | L5: =INDEX(TCS!$B:$K,MATCH("Return on Capital Emp",TCS!$A:$A,0),MATCH($B5,TCS!$B$16:$K$16,0)) -> 0.4749186
A6: TCS | B6: 44286 | C6: =INDEX(TCS!$B:$K,MATCH("Sales",TCS!$A:$A,0),MATCH($B6,TCS!$B$16:$K$16,0)) -> 164177 | D6: =INDEX(TCS!$B:$K,MATCH("Net profit",TCS!$A:$A,0),MATCH($B6,TCS!$B$16:$K$16,0)) -> 32430 | E6: =TCS!F66 -> 129992 | F6: =INDEX(TCS!$B:$K,MATCH("Equity Share Capital",TCS!$A:$A,0),MATCH($B6,TCS!$B$16:$K$16,0)) -> 370 | G6: =INDEX(TCS!$B:$K,MATCH("Reserves",TCS!$A:$A,0),MATCH($B6,TCS!$B$16:$K$16,0)) -> 86063 | H6: =F6+G6 -> 86433 | I6: =INDEX(TCS!$B:$K,MATCH("Borrowings",TCS!$A:$A,0),MATCH($B6,TCS!$B$16:$K$16,0)) -> 7795 | J6: =INDEX(TCS!$B:$K,MATCH("EPS",TCS!$A:$A,0),MATCH($B6,TCS!$B$16:$K$16,0)) -> 87.669974 | K6: =INDEX(TCS!$B:$K,MATCH("Return on Equity",TCS!$A:$A,0),MATCH($B6,TCS!$B$16:$K$16,0)) -> 0.37520392 | L6: =INDEX(TCS!$B:$K,MATCH("Return on Capital Emp",TCS!$A:$A,0),MATCH($B6,TCS!$B$16:$K$16,0)) -> 0.47603577
A7: TCS | B7: 44651 | C7: =INDEX(TCS!$B:$K,MATCH("Sales",TCS!$A:$A,0),MATCH($B7,TCS!$B$16:$K$16,0)) -> 191754 | D7: =INDEX(TCS!$B:$K,MATCH("Net profit",TCS!$A:$A,0),MATCH($B7,TCS!$B$16:$K$16,0)) -> 38327 | E7: =TCS!G66 -> 140924 | F7: =INDEX(TCS!$B:$K,MATCH("Equity Share Capital",TCS!$A:$A,0),MATCH($B7,TCS!$B$16:$K$16,0)) -> 366 | G7: =INDEX(TCS!$B:$K,MATCH("Reserves",TCS!$A:$A,0),MATCH($B7,TCS!$B$16:$K$16,0)) -> 88773 | H7: =F7+G7 -> 89139 | I7: =INDEX(TCS!$B:$K,MATCH("Borrowings",TCS!$A:$A,0),MATCH($B7,TCS!$B$16:$K$16,0)) -> 7818 | J7: =INDEX(TCS!$B:$K,MATCH("EPS",TCS!$A:$A,0),MATCH($B7,TCS!$B$16:$K$16,0)) -> 104.74434 | K7: =INDEX(TCS!$B:$K,MATCH("Return on Equity",TCS!$A:$A,0),MATCH($B7,TCS!$B$16:$K$16,0)) -> 0.42996892 | L7: =INDEX(TCS!$B:$K,MATCH("Return on Capital Emp",TCS!$A:$A,0),MATCH($B7,TCS!$B$16:$K$16,0)) -> 0.5489029
A8: TCS | B8: 45016 | C8: =INDEX(TCS!$B:$K,MATCH("Sales",TCS!$A:$A,0),MATCH($B8,TCS!$B$16:$K$16,0)) -> 225458 | D8: =INDEX(TCS!$B:$K,MATCH("Net profit",TCS!$A:$A,0),MATCH($B8,TCS!$B$16:$K$16,0)) -> 42147 | E8: =TCS!H66 -> 142859 | F8: =INDEX(TCS!$B:$K,MATCH("Equity Share Capital",TCS!$A:$A,0),MATCH($B8,TCS!$B$16:$K$16,0)) -> 366 | G8: =INDEX(TCS!$B:$K,MATCH("Reserves",TCS!$A:$A,0),MATCH($B8,TCS!$B$16:$K$16,0)) -> 90058 | H8: =F8+G8 -> 90424 | I8: =INDEX(TCS!$B:$K,MATCH("Borrowings",TCS!$A:$A,0),MATCH($B8,TCS!$B$16:$K$16,0)) -> 7688 | J8: =INDEX(TCS!$B:$K,MATCH("EPS",TCS!$A:$A,0),MATCH($B8,TCS!$B$16:$K$16,0)) -> 115.18406 | K8: =INDEX(TCS!$B:$K,MATCH("Return on Equity",TCS!$A:$A,0),MATCH($B8,TCS!$B$16:$K$16,0)) -> 0.46610413 | L8: =INDEX(TCS!$B:$K,MATCH("Return on Capital Emp",TCS!$A:$A,0),MATCH($B8,TCS!$B$16:$K$16,0)) -> 0.591442
A9: TCS | B9: 45382 | C9: =INDEX(TCS!$B:$K,MATCH("Sales",TCS!$A:$A,0),MATCH($B9,TCS!$B$16:$K$16,0)) -> 240893 | D9: =INDEX(TCS!$B:$K,MATCH("Net profit",TCS!$A:$A,0),MATCH($B9,TCS!$B$16:$K$16,0)) -> 45908 | E9: =TCS!I66 -> 145472 | F9: =INDEX(TCS!$B:$K,MATCH("Equity Share Capital",TCS!$A:$A,0),MATCH($B9,TCS!$B$16:$K$16,0)) -> 362 | G9: =INDEX(TCS!$B:$K,MATCH("Reserves",TCS!$A:$A,0),MATCH($B9,TCS!$B$16:$K$16,0)) -> 90127 | H9: =F9+G9 -> 90489 | I9: =INDEX(TCS!$B:$K,MATCH("Borrowings",TCS!$A:$A,0),MATCH($B9,TCS!$B$16:$K$16,0)) -> 8021 | J9: =INDEX(TCS!$B:$K,MATCH("EPS",TCS!$A:$A,0),MATCH($B9,TCS!$B$16:$K$16,0)) -> 126.88428 | K9: =INDEX(TCS!$B:$K,MATCH("Return on Equity",TCS!$A:$A,0),MATCH($B9,TCS!$B$16:$K$16,0)) -> 0.50733238 | L9: =INDEX(TCS!$B:$K,MATCH("Return on Capital Emp",TCS!$A:$A,0),MATCH($B9,TCS!$B$16:$K$16,0)) -> 0.63853485
A10: TCS | B10: 45747 | C10: =INDEX(TCS!$B:$K,MATCH("Sales",TCS!$A:$A,0),MATCH($B10,TCS!$B$16:$K$16,0)) -> 255324 | D10: =INDEX(TCS!$B:$K,MATCH("Net profit",TCS!$A:$A,0),MATCH($B10,TCS!$B$16:$K$16,0)) -> 48553 | E10: =TCS!J66 -> 158649 | F10: =INDEX(TCS!$B:$K,MATCH("Equity Share Capital",TCS!$A:$A,0),MATCH($B10,TCS!$B$16:$K$16,0)) -> 362 | G10: =INDEX(TCS!$B:$K,MATCH("Reserves",TCS!$A:$A,0),MATCH($B10,TCS!$B$16:$K$16,0)) -> 94394 | H10: =F10+G10 -> 94756 | I10: =INDEX(TCS!$B:$K,MATCH("Borrowings",TCS!$A:$A,0),MATCH($B10,TCS!$B$16:$K$16,0)) -> 9392 | J10: =INDEX(TCS!$B:$K,MATCH("EPS",TCS!$A:$A,0),MATCH($B10,TCS!$B$16:$K$16,0)) -> 134.19474 | K10: =INDEX(TCS!$B:$K,MATCH("Return on Equity",TCS!$A:$A,0),MATCH($B10,TCS!$B$16:$K$16,0)) -> 0.51240027 | L10: =INDEX(TCS!$B:$K,MATCH("Return on Capital Emp",TCS!$A:$A,0),MATCH($B10,TCS!$B$16:$K$16,0)) -> 0.65259699
A11: TCS | B11: 46112 | C11: =INDEX(TCS!$B:$K,MATCH("Sales",TCS!$A:$A,0),MATCH($B11,TCS!$B$16:$K$16,0)) -> 267021 | D11: =INDEX(TCS!$B:$K,MATCH("Net profit",TCS!$A:$A,0),MATCH($B11,TCS!$B$16:$K$16,0)) -> 49210 | E11: =TCS!K66 -> 181167 | F11: =INDEX(TCS!$B:$K,MATCH("Equity Share Capital",TCS!$A:$A,0),MATCH($B11,TCS!$B$16:$K$16,0)) -> 362 | G11: =INDEX(TCS!$B:$K,MATCH("Reserves",TCS!$A:$A,0),MATCH($B11,TCS!$B$16:$K$16,0)) -> 106878 | H11: =F11+G11 -> 107240 | I11: =INDEX(TCS!$B:$K,MATCH("Borrowings",TCS!$A:$A,0),MATCH($B11,TCS!$B$16:$K$16,0)) -> 11283 | J11: =INDEX(TCS!$B:$K,MATCH("EPS",TCS!$A:$A,0),MATCH($B11,TCS!$B$16:$K$16,0)) -> 136.01061 | K11: =INDEX(TCS!$B:$K,MATCH("Return on Equity",TCS!$A:$A,0),MATCH($B11,TCS!$B$16:$K$16,0)) -> 0.45887728 | L11: =INDEX(TCS!$B:$K,MATCH("Return on Capital Emp",TCS!$A:$A,0),MATCH($B11,TCS!$B$16:$K$16,0)) -> 0.59921588
A12: Infosys | B12: 42825 | C12: =INDEX(Infosys!$B:$K,MATCH("Sales",Infosys!$A:$A,0),MATCH($B2,Infosys!$B$16:$K$16,0)) -> 68484 | D12: =INDEX(Infosys!$B:$K,MATCH("Net profit",Infosys!$A:$A,0),MATCH($B2,Infosys!$B$16:$K$16,0)) -> 14353 | E12: =Infosys!B66 -> 83148 | F12: =INDEX(Infosys!$B:$K,MATCH("Equity Share Capital",Infosys!$A:$A,0),MATCH($B2,Infosys!$B$16:$K$16,0)) -> 1144 | G12: =INDEX(Infosys!$B:$K,MATCH("Reserves",Infosys!$A:$A,0),MATCH($B2,Infosys!$B$16:$K$16,0)) -> 67838 | H12: =F12+G12 -> 68982 | J12: =INDEX(Infosys!$B:$K,MATCH("EPS",Infosys!$A:$A,0),MATCH($B2,Infosys!$B$16:$K$16,0)) -> 31.243606 | K12: =INDEX(Infosys!$B:$K,MATCH("Return on Equity",Infosys!$A:$A,0),MATCH($B2,Infosys!$B$16:$K$16,0)) -> 0.20806877
A13: Infosys | B13: 43190 | C13: =INDEX(Infosys!$B:$K,MATCH("Sales",Infosys!$A:$A,0),MATCH($B3,Infosys!$B$16:$K$16,0)) -> 70522 | D13: =INDEX(Infosys!$B:$K,MATCH("Net profit",Infosys!$A:$A,0),MATCH($B3,Infosys!$B$16:$K$16,0)) -> 16029 | E13: =Infosys!C66 -> 79349 | F13: =INDEX(Infosys!$B:$K,MATCH("Equity Share Capital",Infosys!$A:$A,0),MATCH($B3,Infosys!$B$16:$K$16,0)) -> 1088 | G13: =INDEX(Infosys!$B:$K,MATCH("Reserves",Infosys!$A:$A,0),MATCH($B3,Infosys!$B$16:$K$16,0)) -> 63835 | H13: =F13+G13 -> 64923 | J13: =INDEX(Infosys!$B:$K,MATCH("EPS",Infosys!$A:$A,0),MATCH($B3,Infosys!$B$16:$K$16,0)) -> 36.694748 | K13: =INDEX(Infosys!$B:$K,MATCH("Return on Equity",Infosys!$A:$A,0),MATCH($B3,Infosys!$B$16:$K$16,0)) -> 0.24689247 | L13: =INDEX(Infosys!$B:$K,MATCH("Return on Capital Emp",Infosys!$A:$A,0),MATCH($B3,Infosys!$B$16:$K$16,0)) -> 0.30275195
A14: Infosys | B14: 43555 | C14: =INDEX(Infosys!$B:$K,MATCH("Sales",Infosys!$A:$A,0),MATCH($B4,Infosys!$B$16:$K$16,0)) -> 82675 | D14: =INDEX(Infosys!$B:$K,MATCH("Net profit",Infosys!$A:$A,0),MATCH($B4,Infosys!$B$16:$K$16,0)) -> 15404 | E14: =Infosys!D66 -> 84066 | F14: =INDEX(Infosys!$B:$K,MATCH("Equity Share Capital",Infosys!$A:$A,0),MATCH($B4,Infosys!$B$16:$K$16,0)) -> 2170 | G14: =INDEX(Infosys!$B:$K,MATCH("Reserves",Infosys!$A:$A,0),MATCH($B4,Infosys!$B$16:$K$16,0)) -> 62778 | H14: =F14+G14 -> 64948 | J14: =INDEX(Infosys!$B:$K,MATCH("EPS",Infosys!$A:$A,0),MATCH($B4,Infosys!$B$16:$K$16,0)) -> 35.258303 | K14: =INDEX(Infosys!$B:$K,MATCH("Return on Equity",Infosys!$A:$A,0),MATCH($B4,Infosys!$B$16:$K$16,0)) -> 0.23717435 | L14: =INDEX(Infosys!$B:$K,MATCH("Return on Capital Emp",Infosys!$A:$A,0),MATCH($B4,Infosys!$B$16:$K$16,0)) -> 0.32402923
A15: Infosys | B15: 43921 | C15: =INDEX(Infosys!$B:$K,MATCH("Sales",Infosys!$A:$A,0),MATCH($B5,Infosys!$B$16:$K$16,0)) -> 90791 | D15: =INDEX(Infosys!$B:$K,MATCH("Net profit",Infosys!$A:$A,0),MATCH($B5,Infosys!$B$16:$K$16,0)) -> 16594 | E15: =Infosys!E66 -> 91800 | F15: =INDEX(Infosys!$B:$K,MATCH("Equity Share Capital",Infosys!$A:$A,0),MATCH($B5,Infosys!$B$16:$K$16,0)) -> 2122 | G15: =INDEX(Infosys!$B:$K,MATCH("Reserves",Infosys!$A:$A,0),MATCH($B5,Infosys!$B$16:$K$16,0)) -> 63328 | H15: =F15+G15 -> 65450 | I15: =INDEX(Infosys!$B:$K,MATCH("Borrowings",Infosys!$A:$A,0),MATCH($B5,Infosys!$B$16:$K$16,0)) -> 4633 | J15: =INDEX(Infosys!$B:$K,MATCH("EPS",Infosys!$A:$A,0),MATCH($B5,Infosys!$B$16:$K$16,0)) -> 38.962198 | K15: =INDEX(Infosys!$B:$K,MATCH("Return on Equity",Infosys!$A:$A,0),MATCH($B5,Infosys!$B$16:$K$16,0)) -> 0.25353705 | L15: =INDEX(Infosys!$B:$K,MATCH("Return on Capital Emp",Infosys!$A:$A,0),MATCH($B5,Infosys!$B$16:$K$16,0)) -> 0.32847272
A16: Infosys | B16: 44286 | C16: =INDEX(Infosys!$B:$K,MATCH("Sales",Infosys!$A:$A,0),MATCH($B6,Infosys!$B$16:$K$16,0)) -> 100472 | D16: =INDEX(Infosys!$B:$K,MATCH("Net profit",Infosys!$A:$A,0),MATCH($B6,Infosys!$B$16:$K$16,0)) -> 19351 | E16: =Infosys!F66 -> 107511 | F16: =INDEX(Infosys!$B:$K,MATCH("Equity Share Capital",Infosys!$A:$A,0),MATCH($B6,Infosys!$B$16:$K$16,0)) -> 2124 | G16: =INDEX(Infosys!$B:$K,MATCH("Reserves",Infosys!$A:$A,0),MATCH($B6,Infosys!$B$16:$K$16,0)) -> 74227 | H16: =F16+G16 -> 76351 | I16: =INDEX(Infosys!$B:$K,MATCH("Borrowings",Infosys!$A:$A,0),MATCH($B6,Infosys!$B$16:$K$16,0)) -> 5325 | J16: =INDEX(Infosys!$B:$K,MATCH("EPS",Infosys!$A:$A,0),MATCH($B6,Infosys!$B$16:$K$16,0)) -> 45.41742 | K16: =INDEX(Infosys!$B:$K,MATCH("Return on Equity",Infosys!$A:$A,0),MATCH($B6,Infosys!$B$16:$K$16,0)) -> 0.25344789 | L16: =INDEX(Infosys!$B:$K,MATCH("Return on Capital Emp",Infosys!$A:$A,0),MATCH($B6,Infosys!$B$16:$K$16,0)) -> 0.35349469
A17: Infosys | B17: 44651 | C17: =INDEX(Infosys!$B:$K,MATCH("Sales",Infosys!$A:$A,0),MATCH($B7,Infosys!$B$16:$K$16,0)) -> 121641 | D17: =INDEX(Infosys!$B:$K,MATCH("Net profit",Infosys!$A:$A,0),MATCH($B7,Infosys!$B$16:$K$16,0)) -> 22110 | E17: =Infosys!G66 -> 116729 | F17: =INDEX(Infosys!$B:$K,MATCH("Equity Share Capital",Infosys!$A:$A,0),MATCH($B7,Infosys!$B$16:$K$16,0)) -> 2098 | G17: =INDEX(Infosys!$B:$K,MATCH("Reserves",Infosys!$A:$A,0),MATCH($B7,Infosys!$B$16:$K$16,0)) -> 73252 | H17: =F17+G17 -> 75350 | I17: =INDEX(Infosys!$B:$K,MATCH("Borrowings",Infosys!$A:$A,0),MATCH($B7,Infosys!$B$16:$K$16,0)) -> 5474 | J17: =INDEX(Infosys!$B:$K,MATCH("EPS",Infosys!$A:$A,0),MATCH($B7,Infosys!$B$16:$K$16,0)) -> 52.559013 | K17: =INDEX(Infosys!$B:$K,MATCH("Return on Equity",Infosys!$A:$A,0),MATCH($B7,Infosys!$B$16:$K$16,0)) -> 0.29343066 | L17: =INDEX(Infosys!$B:$K,MATCH("Return on Capital Emp",Infosys!$A:$A,0),MATCH($B7,Infosys!$B$16:$K$16,0)) -> 0.37304615
A18: Infosys | B18: 45016 | C18: =INDEX(Infosys!$B:$K,MATCH("Sales",Infosys!$A:$A,0),MATCH($B8,Infosys!$B$16:$K$16,0)) -> 146767 | D18: =INDEX(Infosys!$B:$K,MATCH("Net profit",Infosys!$A:$A,0),MATCH($B8,Infosys!$B$16:$K$16,0)) -> 24095 | E18: =Infosys!H66 -> 124596 | F18: =INDEX(Infosys!$B:$K,MATCH("Equity Share Capital",Infosys!$A:$A,0),MATCH($B8,Infosys!$B$16:$K$16,0)) -> 2069 | G18: =INDEX(Infosys!$B:$K,MATCH("Reserves",Infosys!$A:$A,0),MATCH($B8,Infosys!$B$16:$K$16,0)) -> 73338 | H18: =F18+G18 -> 75407 | I18: =INDEX(Infosys!$B:$K,MATCH("Borrowings",Infosys!$A:$A,0),MATCH($B8,Infosys!$B$16:$K$16,0)) -> 8299 | J18: =INDEX(Infosys!$B:$K,MATCH("EPS",Infosys!$A:$A,0),MATCH($B8,Infosys!$B$16:$K$16,0)) -> 58.079834 | K18: =INDEX(Infosys!$B:$K,MATCH("Return on Equity",Infosys!$A:$A,0),MATCH($B8,Infosys!$B$16:$K$16,0)) -> 0.31953267 | L18: =INDEX(Infosys!$B:$K,MATCH("Return on Capital Emp",Infosys!$A:$A,0),MATCH($B8,Infosys!$B$16:$K$16,0)) -> 0.40850909
A19: Infosys | B19: 45382 | C19: =INDEX(Infosys!$B:$K,MATCH("Sales",Infosys!$A:$A,0),MATCH($B9,Infosys!$B$16:$K$16,0)) -> 153670 | D19: =INDEX(Infosys!$B:$K,MATCH("Net profit",Infosys!$A:$A,0),MATCH($B9,Infosys!$B$16:$K$16,0)) -> 26233 | E19: =Infosys!I66 -> 136020 | F19: =INDEX(Infosys!$B:$K,MATCH("Equity Share Capital",Infosys!$A:$A,0),MATCH($B9,Infosys!$B$16:$K$16,0)) -> 2071 | G19: =INDEX(Infosys!$B:$K,MATCH("Reserves",Infosys!$A:$A,0),MATCH($B9,Infosys!$B$16:$K$16,0)) -> 86045 | H19: =F19+G19 -> 88116 | I19: =INDEX(Infosys!$B:$K,MATCH("Borrowings",Infosys!$A:$A,0),MATCH($B9,Infosys!$B$16:$K$16,0)) -> 8359 | J19: =INDEX(Infosys!$B:$K,MATCH("EPS",Infosys!$A:$A,0),MATCH($B9,Infosys!$B$16:$K$16,0)) -> 63.198343 | K19: =INDEX(Infosys!$B:$K,MATCH("Return on Equity",Infosys!$A:$A,0),MATCH($B9,Infosys!$B$16:$K$16,0)) -> 0.29770984 | L19: =INDEX(Infosys!$B:$K,MATCH("Return on Capital Emp",Infosys!$A:$A,0),MATCH($B9,Infosys!$B$16:$K$16,0)) -> 0.40468196
A20: Infosys | B20: 45747 | C20: =INDEX(Infosys!$B:$K,MATCH("Sales",Infosys!$A:$A,0),MATCH($B10,Infosys!$B$16:$K$16,0)) -> 162990 | D20: =INDEX(Infosys!$B:$K,MATCH("Net profit",Infosys!$A:$A,0),MATCH($B10,Infosys!$B$16:$K$16,0)) -> 26713 | E20: =Infosys!J66 -> 147795 | F20: =INDEX(Infosys!$B:$K,MATCH("Equity Share Capital",Infosys!$A:$A,0),MATCH($B10,Infosys!$B$16:$K$16,0)) -> 2073 | G20: =INDEX(Infosys!$B:$K,MATCH("Reserves",Infosys!$A:$A,0),MATCH($B10,Infosys!$B$16:$K$16,0)) -> 93745 | H20: =F20+G20 -> 95818 | I20: =INDEX(Infosys!$B:$K,MATCH("Borrowings",Infosys!$A:$A,0),MATCH($B10,Infosys!$B$16:$K$16,0)) -> 8227 | J20: =INDEX(Infosys!$B:$K,MATCH("EPS",Infosys!$A:$A,0),MATCH($B10,Infosys!$B$16:$K$16,0)) -> 64.317531 | K20: =INDEX(Infosys!$B:$K,MATCH("Return on Equity",Infosys!$A:$A,0),MATCH($B10,Infosys!$B$16:$K$16,0)) -> 0.27878895 | L20: =INDEX(Infosys!$B:$K,MATCH("Return on Capital Emp",Infosys!$A:$A,0),MATCH($B10,Infosys!$B$16:$K$16,0)) -> 0.37925394
A21: Infosys | B21: 46112 | C21: =INDEX(Infosys!$B:$K,MATCH("Sales",Infosys!$A:$A,0),MATCH($B11,Infosys!$B$16:$K$16,0)) -> 178650 | D21: =INDEX(Infosys!$B:$K,MATCH("Net profit",Infosys!$A:$A,0),MATCH($B11,Infosys!$B$16:$K$16,0)) -> 29440 | E21: =Infosys!K66 -> 154288 | F21: =INDEX(Infosys!$B:$K,MATCH("Equity Share Capital",Infosys!$A:$A,0),MATCH($B11,Infosys!$B$16:$K$16,0)) -> 2024 | G21: =INDEX(Infosys!$B:$K,MATCH("Reserves",Infosys!$A:$A,0),MATCH($B11,Infosys!$B$16:$K$16,0)) -> 90828 | H21: =F21+G21 -> 92852 | I21: =INDEX(Infosys!$B:$K,MATCH("Borrowings",Infosys!$A:$A,0),MATCH($B11,Infosys!$B$16:$K$16,0)) -> 9176 | J21: =INDEX(Infosys!$B:$K,MATCH("EPS",Infosys!$A:$A,0),MATCH($B11,Infosys!$B$16:$K$16,0)) -> 72.590985 | K21: =INDEX(Infosys!$B:$K,MATCH("Return on Equity",Infosys!$A:$A,0),MATCH($B11,Infosys!$B$16:$K$16,0)) -> 0.31706371 | L21: =INDEX(Infosys!$B:$K,MATCH("Return on Capital Emp",Infosys!$A:$A,0),MATCH($B11,Infosys!$B$16:$K$16,0)) -> 0.39220082
A22: HCLTech | B22: 42825 | C22: =INDEX(HCLTech!$B:$K,MATCH("Sales",HCLTech!$A:$A,0),MATCH($B2,HCLTech!$B$16:$K$16,0)) -> 47568 | D22: =INDEX(HCLTech!$B:$K,MATCH("Net profit",HCLTech!$A:$A,0),MATCH($B2,HCLTech!$B$16:$K$16,0)) -> 8606 | E22: =HCLTech!B66 -> 45762 | F22: =INDEX(HCLTech!$B:$K,MATCH("Equity Share Capital",HCLTech!$A:$A,0),MATCH($B2,HCLTech!$B$16:$K$16,0)) -> 285 | G22: =INDEX(HCLTech!$B:$K,MATCH("Reserves",HCLTech!$A:$A,0),MATCH($B2,HCLTech!$B$16:$K$16,0)) -> 32664 | H22: =F22+G22 -> 32949 | I22: =INDEX(HCLTech!$B:$K,MATCH("Borrowings",HCLTech!$A:$A,0),MATCH($B2,HCLTech!$B$16:$K$16,0)) -> 582 | J22: =INDEX(HCLTech!$B:$K,MATCH("EPS",HCLTech!$A:$A,0),MATCH($B2,HCLTech!$B$16:$K$16,0)) -> 30.158396 | K22: =INDEX(HCLTech!$B:$K,MATCH("Return on Equity",HCLTech!$A:$A,0),MATCH($B2,HCLTech!$B$16:$K$16,0)) -> 0.26119154
A23: HCLTech | B23: 43190 | C23: =INDEX(HCLTech!$B:$K,MATCH("Sales",HCLTech!$A:$A,0),MATCH($B3,HCLTech!$B$16:$K$16,0)) -> 50569 | D23: =INDEX(HCLTech!$B:$K,MATCH("Net profit",HCLTech!$A:$A,0),MATCH($B3,HCLTech!$B$16:$K$16,0)) -> 8721 | E23: =HCLTech!C66 -> 47989 | F23: =INDEX(HCLTech!$B:$K,MATCH("Equity Share Capital",HCLTech!$A:$A,0),MATCH($B3,HCLTech!$B$16:$K$16,0)) -> 278 | G23: =INDEX(HCLTech!$B:$K,MATCH("Reserves",HCLTech!$A:$A,0),MATCH($B3,HCLTech!$B$16:$K$16,0)) -> 36108 | H23: =F23+G23 -> 36386 | I23: =INDEX(HCLTech!$B:$K,MATCH("Borrowings",HCLTech!$A:$A,0),MATCH($B3,HCLTech!$B$16:$K$16,0)) -> 557 | J23: =INDEX(HCLTech!$B:$K,MATCH("EPS",HCLTech!$A:$A,0),MATCH($B3,HCLTech!$B$16:$K$16,0)) -> 31.319806 | K23: =INDEX(HCLTech!$B:$K,MATCH("Return on Equity",HCLTech!$A:$A,0),MATCH($B3,HCLTech!$B$16:$K$16,0)) -> 0.2396801 | L23: =INDEX(HCLTech!$B:$K,MATCH("Return on Capital Emp",HCLTech!$A:$A,0),MATCH($B3,HCLTech!$B$16:$K$16,0)) -> 0.31481114
A24: HCLTech | B24: 43555 | C24: =INDEX(HCLTech!$B:$K,MATCH("Sales",HCLTech!$A:$A,0),MATCH($B4,HCLTech!$B$16:$K$16,0)) -> 60427 | D24: =INDEX(HCLTech!$B:$K,MATCH("Net profit",HCLTech!$A:$A,0),MATCH($B4,HCLTech!$B$16:$K$16,0)) -> 10120 | E24: =HCLTech!D66 -> 58349 | F24: =INDEX(HCLTech!$B:$K,MATCH("Equity Share Capital",HCLTech!$A:$A,0),MATCH($B4,HCLTech!$B$16:$K$16,0)) -> 271 | G24: =INDEX(HCLTech!$B:$K,MATCH("Reserves",HCLTech!$A:$A,0),MATCH($B4,HCLTech!$B$16:$K$16,0)) -> 41095 | H24: =F24+G24 -> 41366 | I24: =INDEX(HCLTech!$B:$K,MATCH("Borrowings",HCLTech!$A:$A,0),MATCH($B4,HCLTech!$B$16:$K$16,0)) -> 4195 | J24: =INDEX(HCLTech!$B:$K,MATCH("EPS",HCLTech!$A:$A,0),MATCH($B4,HCLTech!$B$16:$K$16,0)) -> 37.30738 | K24: =INDEX(HCLTech!$B:$K,MATCH("Return on Equity",HCLTech!$A:$A,0),MATCH($B4,HCLTech!$B$16:$K$16,0)) -> 0.24464536 | L24: =INDEX(HCLTech!$B:$K,MATCH("Return on Capital Emp",HCLTech!$A:$A,0),MATCH($B4,HCLTech!$B$16:$K$16,0)) -> 0.31019102
A25: HCLTech | B25: 43921 | C25: =INDEX(HCLTech!$B:$K,MATCH("Sales",HCLTech!$A:$A,0),MATCH($B5,HCLTech!$B$16:$K$16,0)) -> 70676 | D25: =INDEX(HCLTech!$B:$K,MATCH("Net profit",HCLTech!$A:$A,0),MATCH($B5,HCLTech!$B$16:$K$16,0)) -> 11057 | E25: =HCLTech!E66 -> 82819 | F25: =INDEX(HCLTech!$B:$K,MATCH("Equity Share Capital",HCLTech!$A:$A,0),MATCH($B5,HCLTech!$B$16:$K$16,0)) -> 543 | G25: =INDEX(HCLTech!$B:$K,MATCH("Reserves",HCLTech!$A:$A,0),MATCH($B5,HCLTech!$B$16:$K$16,0)) -> 50724 | H25: =F25+G25 -> 51267 | I25: =INDEX(HCLTech!$B:$K,MATCH("Borrowings",HCLTech!$A:$A,0),MATCH($B5,HCLTech!$B$16:$K$16,0)) -> 7986 | J25: =INDEX(HCLTech!$B:$K,MATCH("EPS",HCLTech!$A:$A,0),MATCH($B5,HCLTech!$B$16:$K$16,0)) -> 40.745108 | K25: =INDEX(HCLTech!$B:$K,MATCH("Return on Equity",HCLTech!$A:$A,0),MATCH($B5,HCLTech!$B$16:$K$16,0)) -> 0.2156748 | L25: =INDEX(HCLTech!$B:$K,MATCH("Return on Capital Emp",HCLTech!$A:$A,0),MATCH($B5,HCLTech!$B$16:$K$16,0)) -> 0.27639437
A26: HCLTech | B26: 44286 | C26: =INDEX(HCLTech!$B:$K,MATCH("Sales",HCLTech!$A:$A,0),MATCH($B6,HCLTech!$B$16:$K$16,0)) -> 75379 | D26: =INDEX(HCLTech!$B:$K,MATCH("Net profit",HCLTech!$A:$A,0),MATCH($B6,HCLTech!$B$16:$K$16,0)) -> 11145 | E26: =HCLTech!F66 -> 86047 | F26: =INDEX(HCLTech!$B:$K,MATCH("Equity Share Capital",HCLTech!$A:$A,0),MATCH($B6,HCLTech!$B$16:$K$16,0)) -> 543 | G26: =INDEX(HCLTech!$B:$K,MATCH("Reserves",HCLTech!$A:$A,0),MATCH($B6,HCLTech!$B$16:$K$16,0)) -> 59370 | H26: =F26+G26 -> 59913 | I26: =INDEX(HCLTech!$B:$K,MATCH("Borrowings",HCLTech!$A:$A,0),MATCH($B6,HCLTech!$B$16:$K$16,0)) -> 6864 | J26: =INDEX(HCLTech!$B:$K,MATCH("EPS",HCLTech!$A:$A,0),MATCH($B6,HCLTech!$B$16:$K$16,0)) -> 41.069389 | K26: =INDEX(HCLTech!$B:$K,MATCH("Return on Equity",HCLTech!$A:$A,0),MATCH($B6,HCLTech!$B$16:$K$16,0)) -> 0.18601973 | L26: =INDEX(HCLTech!$B:$K,MATCH("Return on Capital Emp",HCLTech!$A:$A,0),MATCH($B6,HCLTech!$B$16:$K$16,0)) -> 0.2596842
A27: HCLTech | B27: 44651 | C27: =INDEX(HCLTech!$B:$K,MATCH("Sales",HCLTech!$A:$A,0),MATCH($B7,HCLTech!$B$16:$K$16,0)) -> 85651 | D27: =INDEX(HCLTech!$B:$K,MATCH("Net profit",HCLTech!$A:$A,0),MATCH($B7,HCLTech!$B$16:$K$16,0)) -> 13499 | E27: =HCLTech!G66 -> 88921 | F27: =INDEX(HCLTech!$B:$K,MATCH("Equity Share Capital",HCLTech!$A:$A,0),MATCH($B7,HCLTech!$B$16:$K$16,0)) -> 543 | G27: =INDEX(HCLTech!$B:$K,MATCH("Reserves",HCLTech!$A:$A,0),MATCH($B7,HCLTech!$B$16:$K$16,0)) -> 61371 | H27: =F27+G27 -> 61914 | I27: =INDEX(HCLTech!$B:$K,MATCH("Borrowings",HCLTech!$A:$A,0),MATCH($B7,HCLTech!$B$16:$K$16,0)) -> 6343 | J27: =INDEX(HCLTech!$B:$K,MATCH("EPS",HCLTech!$A:$A,0),MATCH($B7,HCLTech!$B$16:$K$16,0)) -> 49.743892 | K27: =INDEX(HCLTech!$B:$K,MATCH("Return on Equity",HCLTech!$A:$A,0),MATCH($B7,HCLTech!$B$16:$K$16,0)) -> 0.21802823 | L27: =INDEX(HCLTech!$B:$K,MATCH("Return on Capital Emp",HCLTech!$A:$A,0),MATCH($B7,HCLTech!$B$16:$K$16,0)) -> 0.25578743
A28: HCLTech | B28: 45016 | C28: =INDEX(HCLTech!$B:$K,MATCH("Sales",HCLTech!$A:$A,0),MATCH($B8,HCLTech!$B$16:$K$16,0)) -> 101456 | D28: =INDEX(HCLTech!$B:$K,MATCH("Net profit",HCLTech!$A:$A,0),MATCH($B8,HCLTech!$B$16:$K$16,0)) -> 14851 | E28: =HCLTech!H66 -> 93250 | F28: =INDEX(HCLTech!$B:$K,MATCH("Equity Share Capital",HCLTech!$A:$A,0),MATCH($B8,HCLTech!$B$16:$K$16,0)) -> 543 | G28: =INDEX(HCLTech!$B:$K,MATCH("Reserves",HCLTech!$A:$A,0),MATCH($B8,HCLTech!$B$16:$K$16,0)) -> 64862 | H28: =F28+G28 -> 65405 | I28: =INDEX(HCLTech!$B:$K,MATCH("Borrowings",HCLTech!$A:$A,0),MATCH($B8,HCLTech!$B$16:$K$16,0)) -> 4794 | J28: =INDEX(HCLTech!$B:$K,MATCH("EPS",HCLTech!$A:$A,0),MATCH($B8,HCLTech!$B$16:$K$16,0)) -> 54.72602 | K28: =INDEX(HCLTech!$B:$K,MATCH("Return on Equity",HCLTech!$A:$A,0),MATCH($B8,HCLTech!$B$16:$K$16,0)) -> 0.22706215 | L28: =INDEX(HCLTech!$B:$K,MATCH("Return on Capital Emp",HCLTech!$A:$A,0),MATCH($B8,HCLTech!$B$16:$K$16,0)) -> 0.28660369
A29: HCLTech | B29: 45382 | C29: =INDEX(HCLTech!$B:$K,MATCH("Sales",HCLTech!$A:$A,0),MATCH($B9,HCLTech!$B$16:$K$16,0)) -> 109913 | D29: =INDEX(HCLTech!$B:$K,MATCH("Net profit",HCLTech!$A:$A,0),MATCH($B9,HCLTech!$B$16:$K$16,0)) -> 15702 | E29: =HCLTech!I66 -> 99006 | F29: =INDEX(HCLTech!$B:$K,MATCH("Equity Share Capital",HCLTech!$A:$A,0),MATCH($B9,HCLTech!$B$16:$K$16,0)) -> 543 | G29: =INDEX(HCLTech!$B:$K,MATCH("Reserves",HCLTech!$A:$A,0),MATCH($B9,HCLTech!$B$16:$K$16,0)) -> 67720 | H29: =F29+G29 -> 68263 | I29: =INDEX(HCLTech!$B:$K,MATCH("Borrowings",HCLTech!$A:$A,0),MATCH($B9,HCLTech!$B$16:$K$16,0)) -> 5756 | J29: =INDEX(HCLTech!$B:$K,MATCH("EPS",HCLTech!$A:$A,0),MATCH($B9,HCLTech!$B$16:$K$16,0)) -> 57.86196 | K29: =INDEX(HCLTech!$B:$K,MATCH("Return on Equity",HCLTech!$A:$A,0),MATCH($B9,HCLTech!$B$16:$K$16,0)) -> 0.23002212 | L29: =INDEX(HCLTech!$B:$K,MATCH("Return on Capital Emp",HCLTech!$A:$A,0),MATCH($B9,HCLTech!$B$16:$K$16,0)) -> 0.29843709
A30: HCLTech | B30: 45747 | C30: =INDEX(HCLTech!$B:$K,MATCH("Sales",HCLTech!$A:$A,0),MATCH($B10,HCLTech!$B$16:$K$16,0)) -> 117055 | D30: =INDEX(HCLTech!$B:$K,MATCH("Net profit",HCLTech!$A:$A,0),MATCH($B10,HCLTech!$B$16:$K$16,0)) -> 17390 | E30: =HCLTech!J66 -> 104480 | F30: =INDEX(HCLTech!$B:$K,MATCH("Equity Share Capital",HCLTech!$A:$A,0),MATCH($B10,HCLTech!$B$16:$K$16,0)) -> 543 | G30: =INDEX(HCLTech!$B:$K,MATCH("Reserves",HCLTech!$A:$A,0),MATCH($B10,HCLTech!$B$16:$K$16,0)) -> 69112 | H30: =F30+G30 -> 69655 | I30: =INDEX(HCLTech!$B:$K,MATCH("Borrowings",HCLTech!$A:$A,0),MATCH($B10,HCLTech!$B$16:$K$16,0)) -> 6276 | J30: =INDEX(HCLTech!$B:$K,MATCH("EPS",HCLTech!$A:$A,0),MATCH($B10,HCLTech!$B$16:$K$16,0)) -> 64.082249 | K30: =INDEX(HCLTech!$B:$K,MATCH("Return on Equity",HCLTech!$A:$A,0),MATCH($B10,HCLTech!$B$16:$K$16,0)) -> 0.24965903 | L30: =INDEX(HCLTech!$B:$K,MATCH("Return on Capital Emp",HCLTech!$A:$A,0),MATCH($B10,HCLTech!$B$16:$K$16,0)) -> 0.31883961
A31: HCLTech | B31: 46112 | C31: =INDEX(HCLTech!$B:$K,MATCH("Sales",HCLTech!$A:$A,0),MATCH($B11,HCLTech!$B$16:$K$16,0)) -> 130144 | D31: =INDEX(HCLTech!$B:$K,MATCH("Net profit",HCLTech!$A:$A,0),MATCH($B11,HCLTech!$B$16:$K$16,0)) -> 16642 | E31: =HCLTech!K66 -> 116258 | F31: =INDEX(HCLTech!$B:$K,MATCH("Equity Share Capital",HCLTech!$A:$A,0),MATCH($B11,HCLTech!$B$16:$K$16,0)) -> 543 | G31: =INDEX(HCLTech!$B:$K,MATCH("Reserves",HCLTech!$A:$A,0),MATCH($B11,HCLTech!$B$16:$K$16,0)) -> 74622 | H31: =F31+G31 -> 75165 | I31: =INDEX(HCLTech!$B:$K,MATCH("Borrowings",HCLTech!$A:$A,0),MATCH($B11,HCLTech!$B$16:$K$16,0)) -> 5215 | J31: =INDEX(HCLTech!$B:$K,MATCH("EPS",HCLTech!$A:$A,0),MATCH($B11,HCLTech!$B$16:$K$16,0)) -> 61.325865 | K31: =INDEX(HCLTech!$B:$K,MATCH("Return on Equity",HCLTech!$A:$A,0),MATCH($B11,HCLTech!$B$16:$K$16,0)) -> 0.22140624 | L31: =INDEX(HCLTech!$B:$K,MATCH("Return on Capital Emp",HCLTech!$A:$A,0),MATCH($B11,HCLTech!$B$16:$K$16,0)) -> 0.29391406
A32: Wipro | B32: 42825 | C32: =INDEX(Wipro!$B:$K,MATCH("Sales",Wipro!$A:$A,0),MATCH($B2,Wipro!$B$16:$K$16,0)) -> 55448.4 | D32: =INDEX(Wipro!$B:$K,MATCH("Net profit",Wipro!$A:$A,0),MATCH($B2,Wipro!$B$16:$K$16,0)) -> 8493.1 | E32: =Wipro!B66 -> 78672.2 | F32: =INDEX(Wipro!$B:$K,MATCH("Equity Share Capital",Wipro!$A:$A,0),MATCH($B2,Wipro!$B$16:$K$16,0)) -> 486.1 | G32: =INDEX(Wipro!$B:$K,MATCH("Reserves",Wipro!$A:$A,0),MATCH($B2,Wipro!$B$16:$K$16,0)) -> 51184.1 | H32: =F32+G32 -> 51670.2 | I32: =INDEX(Wipro!$B:$K,MATCH("Borrowings",Wipro!$A:$A,0),MATCH($B2,Wipro!$B$16:$K$16,0)) -> 14241.2 | J32: =INDEX(Wipro!$B:$K,MATCH("EPS",Wipro!$A:$A,0),MATCH($B2,Wipro!$B$16:$K$16,0)) -> 6.5508916 | K32: =INDEX(Wipro!$B:$K,MATCH("Return on Equity",Wipro!$A:$A,0),MATCH($B2,Wipro!$B$16:$K$16,0)) -> 0.16437134
A33: Wipro | B33: 43190 | C33: =INDEX(Wipro!$B:$K,MATCH("Sales",Wipro!$A:$A,0),MATCH($B3,Wipro!$B$16:$K$16,0)) -> 54487.1 | D33: =INDEX(Wipro!$B:$K,MATCH("Net profit",Wipro!$A:$A,0),MATCH($B3,Wipro!$B$16:$K$16,0)) -> 8002.8 | E33: =Wipro!C66 -> 75390.8 | F33: =INDEX(Wipro!$B:$K,MATCH("Equity Share Capital",Wipro!$A:$A,0),MATCH($B3,Wipro!$B$16:$K$16,0)) -> 904.8 | G33: =INDEX(Wipro!$B:$K,MATCH("Reserves",Wipro!$A:$A,0),MATCH($B3,Wipro!$B$16:$K$16,0)) -> 47021.5 | H33: =F33+G33 -> 47926.3 | I33: =INDEX(Wipro!$B:$K,MATCH("Borrowings",Wipro!$A:$A,0),MATCH($B3,Wipro!$B$16:$K$16,0)) -> 13901.2 | J33: =INDEX(Wipro!$B:$K,MATCH("EPS",Wipro!$A:$A,0),MATCH($B3,Wipro!$B$16:$K$16,0)) -> 6.6338956 | K33: =INDEX(Wipro!$B:$K,MATCH("Return on Equity",Wipro!$A:$A,0),MATCH($B3,Wipro!$B$16:$K$16,0)) -> 0.16698139 | L33: =INDEX(Wipro!$B:$K,MATCH("Return on Capital Emp",Wipro!$A:$A,0),MATCH($B3,Wipro!$B$16:$K$16,0)) -> 0.16948948
A34: Wipro | B34: 43555 | C34: =INDEX(Wipro!$B:$K,MATCH("Sales",Wipro!$A:$A,0),MATCH($B4,Wipro!$B$16:$K$16,0)) -> 59018.9 | D34: =INDEX(Wipro!$B:$K,MATCH("Net profit",Wipro!$A:$A,0),MATCH($B4,Wipro!$B$16:$K$16,0)) -> 9003.7 | E34: =Wipro!D66 -> 82586.4 | F34: =INDEX(Wipro!$B:$K,MATCH("Equity Share Capital",Wipro!$A:$A,0),MATCH($B4,Wipro!$B$16:$K$16,0)) -> 1206.8 | G34: =INDEX(Wipro!$B:$K,MATCH("Reserves",Wipro!$A:$A,0),MATCH($B4,Wipro!$B$16:$K$16,0)) -> 55215.8 | H34: =F34+G34 -> 56422.6 | I34: =INDEX(Wipro!$B:$K,MATCH("Borrowings",Wipro!$A:$A,0),MATCH($B4,Wipro!$B$16:$K$16,0)) -> 9946.7 | J34: =INDEX(Wipro!$B:$K,MATCH("EPS",Wipro!$A:$A,0),MATCH($B4,Wipro!$B$16:$K$16,0)) -> 7.4608673 | K34: =INDEX(Wipro!$B:$K,MATCH("Return on Equity",Wipro!$A:$A,0),MATCH($B4,Wipro!$B$16:$K$16,0)) -> 0.15957613 | L34: =INDEX(Wipro!$B:$K,MATCH("Return on Capital Emp",Wipro!$A:$A,0),MATCH($B4,Wipro!$B$16:$K$16,0)) -> 0.19157576
A35: Wipro | B35: 43921 | C35: =INDEX(Wipro!$B:$K,MATCH("Sales",Wipro!$A:$A,0),MATCH($B5,Wipro!$B$16:$K$16,0)) -> 61137.6 | D35: =INDEX(Wipro!$B:$K,MATCH("Net profit",Wipro!$A:$A,0),MATCH($B5,Wipro!$B$16:$K$16,0)) -> 9722.3 | E35: =Wipro!E66 -> 80999.6 | F35: =INDEX(Wipro!$B:$K,MATCH("Equity Share Capital",Wipro!$A:$A,0),MATCH($B5,Wipro!$B$16:$K$16,0)) -> 1142.7 | G35: =INDEX(Wipro!$B:$K,MATCH("Reserves",Wipro!$A:$A,0),MATCH($B5,Wipro!$B$16:$K$16,0)) -> 54179 | H35: =F35+G35 -> 55321.7 | I35: =INDEX(Wipro!$B:$K,MATCH("Borrowings",Wipro!$A:$A,0),MATCH($B5,Wipro!$B$16:$K$16,0)) -> 9724 | J35: =INDEX(Wipro!$B:$K,MATCH("EPS",Wipro!$A:$A,0),MATCH($B5,Wipro!$B$16:$K$16,0)) -> 8.5084058 | K35: =INDEX(Wipro!$B:$K,MATCH("Return on Equity",Wipro!$A:$A,0),MATCH($B5,Wipro!$B$16:$K$16,0)) -> 0.17574116 | L35: =INDEX(Wipro!$B:$K,MATCH("Return on Capital Emp",Wipro!$A:$A,0),MATCH($B5,Wipro!$B$16:$K$16,0)) -> 0.19761367
A36: Wipro | B36: 44286 | C36: =INDEX(Wipro!$B:$K,MATCH("Sales",Wipro!$A:$A,0),MATCH($B6,Wipro!$B$16:$K$16,0)) -> 61934.9 | D36: =INDEX(Wipro!$B:$K,MATCH("Net profit",Wipro!$A:$A,0),MATCH($B6,Wipro!$B$16:$K$16,0)) -> 10796.4 | E36: =Wipro!F66 -> 82565.8 | F36: =INDEX(Wipro!$B:$K,MATCH("Equity Share Capital",Wipro!$A:$A,0),MATCH($B6,Wipro!$B$16:$K$16,0)) -> 1095.8 | G36: =INDEX(Wipro!$B:$K,MATCH("Reserves",Wipro!$A:$A,0),MATCH($B6,Wipro!$B$16:$K$16,0)) -> 53805.2 | H36: =F36+G36 -> 54901 | I36: =INDEX(Wipro!$B:$K,MATCH("Borrowings",Wipro!$A:$A,0),MATCH($B6,Wipro!$B$16:$K$16,0)) -> 10451.4 | J36: =INDEX(Wipro!$B:$K,MATCH("EPS",Wipro!$A:$A,0),MATCH($B6,Wipro!$B$16:$K$16,0)) -> 9.8522581 | K36: =INDEX(Wipro!$B:$K,MATCH("Return on Equity",Wipro!$A:$A,0),MATCH($B6,Wipro!$B$16:$K$16,0)) -> 0.19665216 | L36: =INDEX(Wipro!$B:$K,MATCH("Return on Capital Emp",Wipro!$A:$A,0),MATCH($B6,Wipro!$B$16:$K$16,0)) -> 0.22104156
A37: Wipro | B37: 44651 | C37: =INDEX(Wipro!$B:$K,MATCH("Sales",Wipro!$A:$A,0),MATCH($B7,Wipro!$B$16:$K$16,0)) -> 79312 | D37: =INDEX(Wipro!$B:$K,MATCH("Net profit",Wipro!$A:$A,0),MATCH($B7,Wipro!$B$16:$K$16,0)) -> 12229.6 | E37: =Wipro!G66 -> 107275.6 | F37: =INDEX(Wipro!$B:$K,MATCH("Equity Share Capital",Wipro!$A:$A,0),MATCH($B7,Wipro!$B$16:$K$16,0)) -> 1096.4 | G37: =INDEX(Wipro!$B:$K,MATCH("Reserves",Wipro!$A:$A,0),MATCH($B7,Wipro!$B$16:$K$16,0)) -> 64306.6 | H37: =F37+G37 -> 65403 | I37: =INDEX(Wipro!$B:$K,MATCH("Borrowings",Wipro!$A:$A,0),MATCH($B7,Wipro!$B$16:$K$16,0)) -> 17592.9 | J37: =INDEX(Wipro!$B:$K,MATCH("EPS",Wipro!$A:$A,0),MATCH($B7,Wipro!$B$16:$K$16,0)) -> 11.154222 | K37: =INDEX(Wipro!$B:$K,MATCH("Return on Equity",Wipro!$A:$A,0),MATCH($B7,Wipro!$B$16:$K$16,0)) -> 0.18698836 | L37: =INDEX(Wipro!$B:$K,MATCH("Return on Capital Emp",Wipro!$A:$A,0),MATCH($B7,Wipro!$B$16:$K$16,0)) -> 0.21130407
A38: Wipro | B38: 45016 | C38: =INDEX(Wipro!$B:$K,MATCH("Sales",Wipro!$A:$A,0),MATCH($B8,Wipro!$B$16:$K$16,0)) -> 90487.6 | D38: =INDEX(Wipro!$B:$K,MATCH("Net profit",Wipro!$A:$A,0),MATCH($B8,Wipro!$B$16:$K$16,0)) -> 11350 | E38: =Wipro!H66 -> 116923.7 | F38: =INDEX(Wipro!$B:$K,MATCH("Equity Share Capital",Wipro!$A:$A,0),MATCH($B8,Wipro!$B$16:$K$16,0)) -> 1097.6 | G38: =INDEX(Wipro!$B:$K,MATCH("Reserves",Wipro!$A:$A,0),MATCH($B8,Wipro!$B$16:$K$16,0)) -> 76570.3 | H38: =F38+G38 -> 77667.9 | I38: =INDEX(Wipro!$B:$K,MATCH("Borrowings",Wipro!$A:$A,0),MATCH($B8,Wipro!$B$16:$K$16,0)) -> 17466.6 | J38: =INDEX(Wipro!$B:$K,MATCH("EPS",Wipro!$A:$A,0),MATCH($B8,Wipro!$B$16:$K$16,0)) -> 10.340932 | K38: =INDEX(Wipro!$B:$K,MATCH("Return on Equity",Wipro!$A:$A,0),MATCH($B8,Wipro!$B$16:$K$16,0)) -> 0.14613502 | L38: =INDEX(Wipro!$B:$K,MATCH("Return on Capital Emp",Wipro!$A:$A,0),MATCH($B8,Wipro!$B$16:$K$16,0)) -> 0.17709947
A39: Wipro | B39: 45382 | C39: =INDEX(Wipro!$B:$K,MATCH("Sales",Wipro!$A:$A,0),MATCH($B9,Wipro!$B$16:$K$16,0)) -> 89760.3 | D39: =INDEX(Wipro!$B:$K,MATCH("Net profit",Wipro!$A:$A,0),MATCH($B9,Wipro!$B$16:$K$16,0)) -> 11045.2 | E39: =Wipro!I66 -> 114608.9 | F39: =INDEX(Wipro!$B:$K,MATCH("Equity Share Capital",Wipro!$A:$A,0),MATCH($B9,Wipro!$B$16:$K$16,0)) -> 1045 | G39: =INDEX(Wipro!$B:$K,MATCH("Reserves",Wipro!$A:$A,0),MATCH($B9,Wipro!$B$16:$K$16,0)) -> 73488 | H39: =F39+G39 -> 74533 | I39: =INDEX(Wipro!$B:$K,MATCH("Borrowings",Wipro!$A:$A,0),MATCH($B9,Wipro!$B$16:$K$16,0)) -> 16464.9 | J39: =INDEX(Wipro!$B:$K,MATCH("EPS",Wipro!$A:$A,0),MATCH($B9,Wipro!$B$16:$K$16,0)) -> 10.569266 | K39: =INDEX(Wipro!$B:$K,MATCH("Return on Equity",Wipro!$A:$A,0),MATCH($B9,Wipro!$B$16:$K$16,0)) -> 0.14819208 | L39: =INDEX(Wipro!$B:$K,MATCH("Return on Capital Emp",Wipro!$A:$A,0),MATCH($B9,Wipro!$B$16:$K$16,0)) -> 0.1716649
A40: Wipro | B40: 45747 | C40: =INDEX(Wipro!$B:$K,MATCH("Sales",Wipro!$A:$A,0),MATCH($B10,Wipro!$B$16:$K$16,0)) -> 89088.4 | D40: =INDEX(Wipro!$B:$K,MATCH("Net profit",Wipro!$A:$A,0),MATCH($B10,Wipro!$B$16:$K$16,0)) -> 13135.4 | E40: =Wipro!J66 -> 127929.1 | F40: =INDEX(Wipro!$B:$K,MATCH("Equity Share Capital",Wipro!$A:$A,0),MATCH($B10,Wipro!$B$16:$K$16,0)) -> 2094.4 | G40: =INDEX(Wipro!$B:$K,MATCH("Reserves",Wipro!$A:$A,0),MATCH($B10,Wipro!$B$16:$K$16,0)) -> 80269.7 | H40: =F40+G40 -> 82364.1 | I40: =INDEX(Wipro!$B:$K,MATCH("Borrowings",Wipro!$A:$A,0),MATCH($B10,Wipro!$B$16:$K$16,0)) -> 19203.5 | J40: =INDEX(Wipro!$B:$K,MATCH("EPS",Wipro!$A:$A,0),MATCH($B10,Wipro!$B$16:$K$16,0)) -> 12.543234 | K40: =INDEX(Wipro!$B:$K,MATCH("Return on Equity",Wipro!$A:$A,0),MATCH($B10,Wipro!$B$16:$K$16,0)) -> 0.15947968 | L40: =INDEX(Wipro!$B:$K,MATCH("Return on Capital Emp",Wipro!$A:$A,0),MATCH($B10,Wipro!$B$16:$K$16,0)) -> 0.19705191
A41: Wipro | B41: 46112 | C41: =INDEX(Wipro!$B:$K,MATCH("Sales",Wipro!$A:$A,0),MATCH($B11,Wipro!$B$16:$K$16,0)) -> 92624 | D41: =INDEX(Wipro!$B:$K,MATCH("Net profit",Wipro!$A:$A,0),MATCH($B11,Wipro!$B$16:$K$16,0)) -> 13197.4 | E41: =Wipro!K66 -> 140883.5 | F41: =INDEX(Wipro!$B:$K,MATCH("Equity Share Capital",Wipro!$A:$A,0),MATCH($B11,Wipro!$B$16:$K$16,0)) -> 2097.7 | G41: =INDEX(Wipro!$B:$K,MATCH("Reserves",Wipro!$A:$A,0),MATCH($B11,Wipro!$B$16:$K$16,0)) -> 85920.6 | H41: =F41+G41 -> 88018.3 | I41: =INDEX(Wipro!$B:$K,MATCH("Borrowings",Wipro!$A:$A,0),MATCH($B11,Wipro!$B$16:$K$16,0)) -> 20291 | J41: =INDEX(Wipro!$B:$K,MATCH("EPS",Wipro!$A:$A,0),MATCH($B11,Wipro!$B$16:$K$16,0)) -> 12.582853 | K41: =INDEX(Wipro!$B:$K,MATCH("Return on Equity",Wipro!$A:$A,0),MATCH($B11,Wipro!$B$16:$K$16,0)) -> 0.14993927 | L41: =INDEX(Wipro!$B:$K,MATCH("Return on Capital Emp",Wipro!$A:$A,0),MATCH($B11,Wipro!$B$16:$K$16,0)) -> 0.17915168
A42: Tech Mahindra | B42: 42825 | C42: =INDEX(TechM!$B:$K,MATCH("Sales",TechM!$A:$A,0),MATCH($B2,TechM!$B$16:$K$16,0)) -> 29140.8 | D42: =INDEX(TechM!$B:$K,MATCH("Net profit",TechM!$A:$A,0),MATCH($B2,TechM!$B$16:$K$16,0)) -> 2812.9 | E42: =TechM!B66 -> 26057 | F42: =INDEX(TechM!$B:$K,MATCH("Equity Share Capital",TechM!$A:$A,0),MATCH($B2,TechM!$B$16:$K$16,0)) -> 438.8 | G42: =INDEX(TechM!$B:$K,MATCH("Reserves",TechM!$A:$A,0),MATCH($B2,TechM!$B$16:$K$16,0)) -> 15998.4 | H42: =F42+G42 -> 16437.2 | I42: =INDEX(TechM!$B:$K,MATCH("Borrowings",TechM!$A:$A,0),MATCH($B2,TechM!$B$16:$K$16,0)) -> 1366.2 | J42: =INDEX(TechM!$B:$K,MATCH("EPS",TechM!$A:$A,0),MATCH($B2,TechM!$B$16:$K$16,0)) -> 28.876912 | K42: =INDEX(TechM!$B:$K,MATCH("Return on Equity",TechM!$A:$A,0),MATCH($B2,TechM!$B$16:$K$16,0)) -> 0.17113012
A43: Tech Mahindra | B43: 43190 | C43: =INDEX(TechM!$B:$K,MATCH("Sales",TechM!$A:$A,0),MATCH($B3,TechM!$B$16:$K$16,0)) -> 30772.9 | D43: =INDEX(TechM!$B:$K,MATCH("Net profit",TechM!$A:$A,0),MATCH($B3,TechM!$B$16:$K$16,0)) -> 3799.8 | E43: =TechM!C66 -> 30431.4 | F43: =INDEX(TechM!$B:$K,MATCH("Equity Share Capital",TechM!$A:$A,0),MATCH($B3,TechM!$B$16:$K$16,0)) -> 441.7 | G43: =INDEX(TechM!$B:$K,MATCH("Reserves",TechM!$A:$A,0),MATCH($B3,TechM!$B$16:$K$16,0)) -> 18401.1 | H43: =F43+G43 -> 18842.8 | I43: =INDEX(TechM!$B:$K,MATCH("Borrowings",TechM!$A:$A,0),MATCH($B3,TechM!$B$16:$K$16,0)) -> 2396.6 | J43: =INDEX(TechM!$B:$K,MATCH("EPS",TechM!$A:$A,0),MATCH($B3,TechM!$B$16:$K$16,0)) -> 38.785342 | K43: =INDEX(TechM!$B:$K,MATCH("Return on Equity",TechM!$A:$A,0),MATCH($B3,TechM!$B$16:$K$16,0)) -> 0.20165793 | L43: =INDEX(TechM!$B:$K,MATCH("Return on Capital Emp",TechM!$A:$A,0),MATCH($B3,TechM!$B$16:$K$16,0)) -> 0.25823968
A44: Tech Mahindra | B44: 43555 | C44: =INDEX(TechM!$B:$K,MATCH("Sales",TechM!$A:$A,0),MATCH($B4,TechM!$B$16:$K$16,0)) -> 34742.1 | D44: =INDEX(TechM!$B:$K,MATCH("Net profit",TechM!$A:$A,0),MATCH($B4,TechM!$B$16:$K$16,0)) -> 4297.6 | E44: =TechM!D66 -> 33445.8 | F44: =INDEX(TechM!$B:$K,MATCH("Equity Share Capital",TechM!$A:$A,0),MATCH($B4,TechM!$B$16:$K$16,0)) -> 443.7 | G44: =INDEX(TechM!$B:$K,MATCH("Reserves",TechM!$A:$A,0),MATCH($B4,TechM!$B$16:$K$16,0)) -> 19840.7 | H44: =F44+G44 -> 20284.4 | I44: =INDEX(TechM!$B:$K,MATCH("Borrowings",TechM!$A:$A,0),MATCH($B4,TechM!$B$16:$K$16,0)) -> 1995.5 | J44: =INDEX(TechM!$B:$K,MATCH("EPS",TechM!$A:$A,0),MATCH($B4,TechM!$B$16:$K$16,0)) -> 43.701444 | K44: =INDEX(TechM!$B:$K,MATCH("Return on Equity",TechM!$A:$A,0),MATCH($B4,TechM!$B$16:$K$16,0)) -> 0.21186725 | L44: =INDEX(TechM!$B:$K,MATCH("Return on Capital Emp",TechM!$A:$A,0),MATCH($B4,TechM!$B$16:$K$16,0)) -> 0.26086817
A45: Tech Mahindra | B45: 43921 | C45: =INDEX(TechM!$B:$K,MATCH("Sales",TechM!$A:$A,0),MATCH($B5,TechM!$B$16:$K$16,0)) -> 36867.7 | D45: =INDEX(TechM!$B:$K,MATCH("Net profit",TechM!$A:$A,0),MATCH($B5,TechM!$B$16:$K$16,0)) -> 4033 | E45: =TechM!E66 -> 37317.9 | F45: =INDEX(TechM!$B:$K,MATCH("Equity Share Capital",TechM!$A:$A,0),MATCH($B5,TechM!$B$16:$K$16,0)) -> 435.9 | G45: =INDEX(TechM!$B:$K,MATCH("Reserves",TechM!$A:$A,0),MATCH($B5,TechM!$B$16:$K$16,0)) -> 21377.2 | H45: =F45+G45 -> 21813.1 | I45: =INDEX(TechM!$B:$K,MATCH("Borrowings",TechM!$A:$A,0),MATCH($B5,TechM!$B$16:$K$16,0)) -> 3670.5 | J45: =INDEX(TechM!$B:$K,MATCH("EPS",TechM!$A:$A,0),MATCH($B5,TechM!$B$16:$K$16,0)) -> 41.753805 | K45: =INDEX(TechM!$B:$K,MATCH("Return on Equity",TechM!$A:$A,0),MATCH($B5,TechM!$B$16:$K$16,0)) -> 0.1848889 | L45: =INDEX(TechM!$B:$K,MATCH("Return on Capital Emp",TechM!$A:$A,0),MATCH($B5,TechM!$B$16:$K$16,0)) -> 0.21982057
A46: Tech Mahindra | B46: 44286 | C46: =INDEX(TechM!$B:$K,MATCH("Sales",TechM!$A:$A,0),MATCH($B6,TechM!$B$16:$K$16,0)) -> 37855.1 | D46: =INDEX(TechM!$B:$K,MATCH("Net profit",TechM!$A:$A,0),MATCH($B6,TechM!$B$16:$K$16,0)) -> 4428 | E46: =TechM!F66 -> 39601.9 | F46: =INDEX(TechM!$B:$K,MATCH("Equity Share Capital",TechM!$A:$A,0),MATCH($B6,TechM!$B$16:$K$16,0)) -> 437 | G46: =INDEX(TechM!$B:$K,MATCH("Reserves",TechM!$A:$A,0),MATCH($B6,TechM!$B$16:$K$16,0)) -> 24428 | H46: =F46+G46 -> 24865 | I46: =INDEX(TechM!$B:$K,MATCH("Borrowings",TechM!$A:$A,0),MATCH($B6,TechM!$B$16:$K$16,0)) -> 2900.8 | J46: =INDEX(TechM!$B:$K,MATCH("EPS",TechM!$A:$A,0),MATCH($B6,TechM!$B$16:$K$16,0)) -> 45.729629 | K46: =INDEX(TechM!$B:$K,MATCH("Return on Equity",TechM!$A:$A,0),MATCH($B6,TechM!$B$16:$K$16,0)) -> 0.17808164 | L46: =INDEX(TechM!$B:$K,MATCH("Return on Capital Emp",TechM!$A:$A,0),MATCH($B6,TechM!$B$16:$K$16,0)) -> 0.2301209
A47: Tech Mahindra | B47: 44651 | C47: =INDEX(TechM!$B:$K,MATCH("Sales",TechM!$A:$A,0),MATCH($B7,TechM!$B$16:$K$16,0)) -> 44646 | D47: =INDEX(TechM!$B:$K,MATCH("Net profit",TechM!$A:$A,0),MATCH($B7,TechM!$B$16:$K$16,0)) -> 5566.1 | E47: =TechM!G66 -> 44415.5 | F47: =INDEX(TechM!$B:$K,MATCH("Equity Share Capital",TechM!$A:$A,0),MATCH($B7,TechM!$B$16:$K$16,0)) -> 438.8 | G47: =INDEX(TechM!$B:$K,MATCH("Reserves",TechM!$A:$A,0),MATCH($B7,TechM!$B$16:$K$16,0)) -> 26446.9 | H47: =F47+G47 -> 26885.7 | I47: =INDEX(TechM!$B:$K,MATCH("Borrowings",TechM!$A:$A,0),MATCH($B7,TechM!$B$16:$K$16,0)) -> 2618.4 | J47: =INDEX(TechM!$B:$K,MATCH("EPS",TechM!$A:$A,0),MATCH($B7,TechM!$B$16:$K$16,0)) -> 57.276189 | K47: =INDEX(TechM!$B:$K,MATCH("Return on Equity",TechM!$A:$A,0),MATCH($B7,TechM!$B$16:$K$16,0)) -> 0.20702827 | L47: =INDEX(TechM!$B:$K,MATCH("Return on Capital Emp",TechM!$A:$A,0),MATCH($B7,TechM!$B$16:$K$16,0)) -> 0.26592329
A48: Tech Mahindra | B48: 45016 | C48: =INDEX(TechM!$B:$K,MATCH("Sales",TechM!$A:$A,0),MATCH($B8,TechM!$B$16:$K$16,0)) -> 53290.2 | D48: =INDEX(TechM!$B:$K,MATCH("Net profit",TechM!$A:$A,0),MATCH($B8,TechM!$B$16:$K$16,0)) -> 4831.3 | E48: =TechM!H66 -> 45827.2 | F48: =INDEX(TechM!$B:$K,MATCH("Equity Share Capital",TechM!$A:$A,0),MATCH($B8,TechM!$B$16:$K$16,0)) -> 440 | G48: =INDEX(TechM!$B:$K,MATCH("Reserves",TechM!$A:$A,0),MATCH($B8,TechM!$B$16:$K$16,0)) -> 27484.5 | H48: =F48+G48 -> 27924.5 | I48: =INDEX(TechM!$B:$K,MATCH("Borrowings",TechM!$A:$A,0),MATCH($B8,TechM!$B$16:$K$16,0)) -> 2740.2 | J48: =INDEX(TechM!$B:$K,MATCH("EPS",TechM!$A:$A,0),MATCH($B8,TechM!$B$16:$K$16,0)) -> 49.597577 | K48: =INDEX(TechM!$B:$K,MATCH("Return on Equity",TechM!$A:$A,0),MATCH($B8,TechM!$B$16:$K$16,0)) -> 0.17301295 | L48: =INDEX(TechM!$B:$K,MATCH("Return on Capital Emp",TechM!$A:$A,0),MATCH($B8,TechM!$B$16:$K$16,0)) -> 0.22507014
A49: Tech Mahindra | B49: 45382 | C49: =INDEX(TechM!$B:$K,MATCH("Sales",TechM!$A:$A,0),MATCH($B9,TechM!$B$16:$K$16,0)) -> 51995.5 | D49: =INDEX(TechM!$B:$K,MATCH("Net profit",TechM!$A:$A,0),MATCH($B9,TechM!$B$16:$K$16,0)) -> 2357.8 | E49: =TechM!I66 -> 43149.1 | F49: =INDEX(TechM!$B:$K,MATCH("Equity Share Capital",TechM!$A:$A,0),MATCH($B9,TechM!$B$16:$K$16,0)) -> 441.3 | G49: =INDEX(TechM!$B:$K,MATCH("Reserves",TechM!$A:$A,0),MATCH($B9,TechM!$B$16:$K$16,0)) -> 26228.1 | H49: =F49+G49 -> 26669.4 | I49: =INDEX(TechM!$B:$K,MATCH("Borrowings",TechM!$A:$A,0),MATCH($B9,TechM!$B$16:$K$16,0)) -> 2536.7 | J49: =INDEX(TechM!$B:$K,MATCH("EPS",TechM!$A:$A,0),MATCH($B9,TechM!$B$16:$K$16,0)) -> 24.138002 | K49: =INDEX(TechM!$B:$K,MATCH("Return on Equity",TechM!$A:$A,0),MATCH($B9,TechM!$B$16:$K$16,0)) -> 0.088408438 | L49: =INDEX(TechM!$B:$K,MATCH("Return on Capital Emp",TechM!$A:$A,0),MATCH($B9,TechM!$B$16:$K$16,0)) -> 0.12081349
A50: Tech Mahindra | B50: 45747 | C50: =INDEX(TechM!$B:$K,MATCH("Sales",TechM!$A:$A,0),MATCH($B10,TechM!$B$16:$K$16,0)) -> 52988.3 | D50: =INDEX(TechM!$B:$K,MATCH("Net profit",TechM!$A:$A,0),MATCH($B10,TechM!$B$16:$K$16,0)) -> 4251.5 | E50: =TechM!J66 -> 44266.6 | F50: =INDEX(TechM!$B:$K,MATCH("Equity Share Capital",TechM!$A:$A,0),MATCH($B10,TechM!$B$16:$K$16,0)) -> 442.4 | G50: =INDEX(TechM!$B:$K,MATCH("Reserves",TechM!$A:$A,0),MATCH($B10,TechM!$B$16:$K$16,0)) -> 26919.1 | H50: =F50+G50 -> 27361.5 | I50: =INDEX(TechM!$B:$K,MATCH("Borrowings",TechM!$A:$A,0),MATCH($B10,TechM!$B$16:$K$16,0)) -> 2025.2 | J50: =INDEX(TechM!$B:$K,MATCH("EPS",TechM!$A:$A,0),MATCH($B10,TechM!$B$16:$K$16,0)) -> 43.426966 | K50: =INDEX(TechM!$B:$K,MATCH("Return on Equity",TechM!$A:$A,0),MATCH($B10,TechM!$B$16:$K$16,0)) -> 0.15538256 | L50: =INDEX(TechM!$B:$K,MATCH("Return on Capital Emp",TechM!$A:$A,0),MATCH($B10,TechM!$B$16:$K$16,0)) -> 0.20394656
A51: Tech Mahindra | B51: 46112 | C51: =INDEX(TechM!$B:$K,MATCH("Sales",TechM!$A:$A,0),MATCH($B11,TechM!$B$16:$K$16,0)) -> 56815.4 | D51: =INDEX(TechM!$B:$K,MATCH("Net profit",TechM!$A:$A,0),MATCH($B11,TechM!$B$16:$K$16,0)) -> 4810.9 | E51: =TechM!K66 -> 49167.7 | F51: =INDEX(TechM!$B:$K,MATCH("Equity Share Capital",TechM!$A:$A,0),MATCH($B11,TechM!$B$16:$K$16,0)) -> 442.8 | G51: =INDEX(TechM!$B:$K,MATCH("Reserves",TechM!$A:$A,0),MATCH($B11,TechM!$B$16:$K$16,0)) -> 29172.6 | H51: =F51+G51 -> 29615.4 | I51: =INDEX(TechM!$B:$K,MATCH("Borrowings",TechM!$A:$A,0),MATCH($B11,TechM!$B$16:$K$16,0)) -> 2186.2 | J51: =INDEX(TechM!$B:$K,MATCH("EPS",TechM!$A:$A,0),MATCH($B11,TechM!$B$16:$K$16,0)) -> 49.100837 | K51: =INDEX(TechM!$B:$K,MATCH("Return on Equity",TechM!$A:$A,0),MATCH($B11,TechM!$B$16:$K$16,0)) -> 0.16244589 | L51: =INDEX(TechM!$B:$K,MATCH("Return on Capital Emp",TechM!$A:$A,0),MATCH($B11,TechM!$B$16:$K$16,0)) -> 0.22587652

Sheet Final_Data
A1: Company | B1: Year | C1: Revenue | D1: Net Profit | E1: Total Assets | F1: Equity Capital | G1: Reserves | H1: Shareholders' Equity | I1: Borrowings | J1: EPS | K1: ROE | L1: ROCE | M1: Net Profit Margin | N1: ROA | O1: Debt-to-Equity Ratio
A2: TCS | B2: 42825 | C2: 117966 | D2: 26289 | E2: 102333 | F2: 197 | G2: 86017 | H2: 86214 | I2: 289 | J2: 66.708112 | K2: 0.30492727 | M2: =IF(OR(C2="",D2=""),"",D2/C2) -> 0.22285235 | N2: =IF(OR(D2="",E2=""),"",D2/E2) -> 0.2568966 | O2: =IF(OR(I2="",H2=""),"",I2/H2) -> 0.0033521238
A3: TCS | B3: 43190 | C3: 123104 | D3: 25826 | E3: 105126 | F3: 191 | G3: 84937 | H3: 85128 | I3: 247 | J3: 67.455467 | K3: 0.30337844 | L3: 0.39730507 | M3: =IF(OR(C3="",D3=""),"",D3/C3) -> 0.2097901 | N3: =IF(OR(D3="",E3=""),"",D3/E3) -> 0.2456671 | O3: =IF(OR(I3="",H3=""),"",I3/H3) -> 0.002901513
A4: TCS | B4: 43555 | C4: 146463 | D4: 31472 | E4: 113901 | F4: 375 | G4: 89071 | H4: 89446 | I4: 62 | J4: 83.871655 | K4: 0.35185475 | L4: 0.47758787 | M4: =IF(OR(C4="",D4=""),"",D4/C4) -> 0.21488021 | N4: =IF(OR(D4="",E4=""),"",D4/E4) -> 0.27631013 | O4: =IF(OR(I4="",H4=""),"",I4/H4) -> 0.00069315565
A5: TCS | B5: 43921 | C5: 156949 | D5: 32340 | E5: 120127 | F5: 375 | G5: 83751 | H5: 84126 | I5: 8174 | J5: 86.184842 | K5: 0.38442336 | L5: 0.4749186 | M5: =IF(OR(C5="",D5=""),"",D5/C5) -> 0.2060542 | N5: =IF(OR(D5="",E5=""),"",D5/E5) -> 0.26921508 | O5: =IF(OR(I5="",H5=""),"",I5/H5) -> 0.097163778
A6: TCS | B6: 44286 | C6: 164177 | D6: 32430 | E6: 129992 | F6: 370 | G6: 86063 | H6: 86433 | I6: 7795 | J6: 87.669974 | K6: 0.37520392 | L6: 0.47603577 | M6: =IF(OR(C6="",D6=""),"",D6/C6) -> 0.19753071 | N6: =IF(OR(D6="",E6=""),"",D6/E6) -> 0.24947689 | O6: =IF(OR(I6="",H6=""),"",I6/H6) -> 0.090185462
A7: TCS | B7: 44651 | C7: 191754 | D7: 38327 | E7: 140924 | F7: 366 | G7: 88773 | H7: 89139 | I7: 7818 | J7: 104.74434 | K7: 0.42996892 | L7: 0.5489029 | M7: =IF(OR(C7="",D7=""),"",D7/C7) -> 0.19987588 | N7: =IF(OR(D7="",E7=""),"",D7/E7) -> 0.27196929 | O7: =IF(OR(I7="",H7=""),"",I7/H7) -> 0.087705718
A8: TCS | B8: 45016 | C8: 225458 | D8: 42147 | E8: 142859 | F8: 366 | G8: 90058 | H8: 90424 | I8: 7688 | J8: 115.18406 | K8: 0.46610413 | L8: 0.591442 | M8: =IF(OR(C8="",D8=""),"",D8/C8) -> 0.18693947 | N8: =IF(OR(D8="",E8=""),"",D8/E8) -> 0.29502516 | O8: =IF(OR(I8="",H8=""),"",I8/H8) -> 0.085021676
A9: TCS | B9: 45382 | C9: 240893 | D9: 45908 | E9: 145472 | F9: 362 | G9: 90127 | H9: 90489 | I9: 8021 | J9: 126.88428 | K9: 0.50733238 | L9: 0.63853485 | M9: =IF(OR(C9="",D9=""),"",D9/C9) -> 0.19057424 | N9: =IF(OR(D9="",E9=""),"",D9/E9) -> 0.31557963 | O9: =IF(OR(I9="",H9=""),"",I9/H9) -> 0.088640608
A10: TCS | B10: 45747 | C10: 255324 | D10: 48553 | E10: 158649 | F10: 362 | G10: 94394 | H10: 94756 | I10: 9392 | J10: 134.19474 | K10: 0.51240027 | L10: 0.65259699 | M10: =IF(OR(C10="",D10=""),"",D10/C10) -> 0.1901623 | N10: =IF(OR(D10="",E10=""),"",D10/E10) -> 0.30604038 | O10: =IF(OR(I10="",H10=""),"",I10/H10) -> 0.099117734
A11: TCS | B11: 46112 | C11: 267021 | D11: 49210 | E11: 181167 | F11: 362 | G11: 106878 | H11: 107240 | I11: 11283 | J11: 136.01061 | K11: 0.45887728 | L11: 0.59921588 | M11: =IF(OR(C11="",D11=""),"",D11/C11) -> 0.18429262 | N11: =IF(OR(D11="",E11=""),"",D11/E11) -> 0.27162784 | O11: =IF(OR(I11="",H11=""),"",I11/H11) -> 0.10521261
A12: Infosys | B12: 42825 | C12: 68484 | D12: 14353 | E12: 83148 | F12: 1144 | G12: 67838 | H12: 68982 | J12: 31.243606 | K12: 0.20806877 | M12: =IF(OR(C12="",D12=""),"",D12/C12) -> 0.2095818 | N12: =IF(OR(D12="",E12=""),"",D12/E12) -> 0.17261991 | O12: =IF(OR(I12="",H12=""),"",I12/H12)
A13: Infosys | B13: 43190 | C13: 70522 | D13: 16029 | E13: 79349 | F13: 1088 | G13: 63835 | H13: 64923 | J13: 36.694748 | K13: 0.24689247 | L13: 0.30275195 | M13: =IF(OR(C13="",D13=""),"",D13/C13) -> 0.22729077 | N13: =IF(OR(D13="",E13=""),"",D13/E13) -> 0.20200633 | O13: =IF(OR(I13="",H13=""),"",I13/H13)
A14: Infosys | B14: 43555 | C14: 82675 | D14: 15404 | E14: 84066 | F14: 2170 | G14: 62778 | H14: 64948 | J14: 35.258303 | K14: 0.23717435 | L14: 0.32402923 | M14: =IF(OR(C14="",D14=""),"",D14/C14) -> 0.18631993 | N14: =IF(OR(D14="",E14=""),"",D14/E14) -> 0.18323698 | O14: =IF(OR(I14="",H14=""),"",I14/H14)
A15: Infosys | B15: 43921 | C15: 90791 | D15: 16594 | E15: 91800 | F15: 2122 | G15: 63328 | H15: 65450 | I15: 4633 | J15: 38.962198 | K15: 0.25353705 | L15: 0.32847272 | M15: =IF(OR(C15="",D15=""),"",D15/C15) -> 0.18277142 | N15: =IF(OR(D15="",E15=""),"",D15/E15) -> 0.18076253 | O15: =IF(OR(I15="",H15=""),"",I15/H15) -> 0.07078686
A16: Infosys | B16: 44286 | C16: 100472 | D16: 19351 | E16: 107511 | F16: 2124 | G16: 74227 | H16: 76351 | I16: 5325 | J16: 45.41742 | K16: 0.25344789 | L16: 0.35349469 | M16: =IF(OR(C16="",D16=""),"",D16/C16) -> 0.19260092 | N16: =IF(OR(D16="",E16=""),"",D16/E16) -> 0.17999088 | O16: =IF(OR(I16="",H16=""),"",I16/H16) -> 0.069743684
A17: Infosys | B17: 44651 | C17: 121641 | D17: 22110 | E17: 116729 | F17: 2098 | G17: 73252 | H17: 75350 | I17: 5474 | J17: 52.559013 | K17: 0.29343066 | L17: 0.37304615 | M17: =IF(OR(C17="",D17=""),"",D17/C17) -> 0.18176437 | N17: =IF(OR(D17="",E17=""),"",D17/E17) -> 0.18941309 | O17: =IF(OR(I17="",H17=""),"",I17/H17) -> 0.072647644
A18: Infosys | B18: 45016 | C18: 146767 | D18: 24095 | E18: 124596 | F18: 2069 | G18: 73338 | H18: 75407 | I18: 8299 | J18: 58.079834 | K18: 0.31953267 | L18: 0.40850909 | M18: =IF(OR(C18="",D18=""),"",D18/C18) -> 0.16417178 | N18: =IF(OR(D18="",E18=""),"",D18/E18) -> 0.19338502 | O18: =IF(OR(I18="",H18=""),"",I18/H18) -> 0.1100561
A19: Infosys | B19: 45382 | C19: 153670 | D19: 26233 | E19: 136020 | F19: 2071 | G19: 86045 | H19: 88116 | I19: 8359 | J19: 63.198343 | K19: 0.29770984 | L19: 0.40468196 | M19: =IF(OR(C19="",D19=""),"",D19/C19) -> 0.17070996 | N19: =IF(OR(D19="",E19=""),"",D19/E19) -> 0.19286134 | O19: =IF(OR(I19="",H19=""),"",I19/H19) -> 0.094863589
A20: Infosys | B20: 45747 | C20: 162990 | D20: 26713 | E20: 147795 | F20: 2073 | G20: 93745 | H20: 95818 | I20: 8227 | J20: 64.317531 | K20: 0.27878895 | L20: 0.37925394 | M20: =IF(OR(C20="",D20=""),"",D20/C20) -> 0.16389349 | N20: =IF(OR(D20="",E20=""),"",D20/E20) -> 0.1807436 | O20: =IF(OR(I20="",H20=""),"",I20/H20) -> 0.085860694
A21: Infosys | B21: 46112 | C21: 178650 | D21: 29440 | E21: 154288 | F21: 2024 | G21: 90828 | H21: 92852 | I21: 9176 | J21: 72.590985 | K21: 0.31706371 | L21: 0.39220082 | M21: =IF(OR(C21="",D21=""),"",D21/C21) -> 0.16479149 | N21: =IF(OR(D21="",E21=""),"",D21/E21) -> 0.19081199 | O21: =IF(OR(I21="",H21=""),"",I21/H21) -> 0.098823935
A22: HCLTech | B22: 42825 | C22: 47568 | D22: 8606 | E22: 45762 | F22: 285 | G22: 32664 | H22: 32949 | I22: 582 | J22: 30.158396 | K22: 0.26119154 | M22: =IF(OR(C22="",D22=""),"",D22/C22) -> 0.18091995 | N22: =IF(OR(D22="",E22=""),"",D22/E22) -> 0.18805996 | O22: =IF(OR(I22="",H22=""),"",I22/H22) -> 0.017663662
A23: HCLTech | B23: 43190 | C23: 50569 | D23: 8721 | E23: 47989 | F23: 278 | G23: 36108 | H23: 36386 | I23: 557 | J23: 31.319806 | K23: 0.2396801 | L23: 0.31481114 | M23: =IF(OR(C23="",D23=""),"",D23/C23) -> 0.17245743 | N23: =IF(OR(D23="",E23=""),"",D23/E23) -> 0.18172915 | O23: =IF(OR(I23="",H23=""),"",I23/H23) -> 0.015308086
A24: HCLTech | B24: 43555 | C24: 60427 | D24: 10120 | E24: 58349 | F24: 271 | G24: 41095 | H24: 41366 | I24: 4195 | J24: 37.30738 | K24: 0.24464536 | L24: 0.31019102 | M24: =IF(OR(C24="",D24=""),"",D24/C24) -> 0.1674748 | N24: =IF(OR(D24="",E24=""),"",D24/E24) -> 0.17343913 | O24: =IF(OR(I24="",H24=""),"",I24/H24) -> 0.10141179
A25: HCLTech | B25: 43921 | C25: 70676 | D25: 11057 | E25: 82819 | F25: 543 | G25: 50724 | H25: 51267 | I25: 7986 | J25: 40.745108 | K25: 0.2156748 | L25: 0.27639437 | M25: =IF(OR(C25="",D25=""),"",D25/C25) -> 0.15644632 | N25: =IF(OR(D25="",E25=""),"",D25/E25) -> 0.13350801 | O25: =IF(OR(I25="",H25=""),"",I25/H25) -> 0.15577272
A26: HCLTech | B26: 44286 | C26: 75379 | D26: 11145 | E26: 86047 | F26: 543 | G26: 59370 | H26: 59913 | I26: 6864 | J26: 41.069389 | K26: 0.18601973 | L26: 0.2596842 | M26: =IF(OR(C26="",D26=""),"",D26/C26) -> 0.14785285 | N26: =IF(OR(D26="",E26=""),"",D26/E26) -> 0.12952224 | O26: =IF(OR(I26="",H26=""),"",I26/H26) -> 0.11456612
A27: HCLTech | B27: 44651 | C27: 85651 | D27: 13499 | E27: 88921 | F27: 543 | G27: 61371 | H27: 61914 | I27: 6343 | J27: 49.743892 | K27: 0.21802823 | L27: 0.25578743 | M27: =IF(OR(C27="",D27=""),"",D27/C27) -> 0.1576047 | N27: =IF(OR(D27="",E27=""),"",D27/E27) -> 0.15180891 | O27: =IF(OR(I27="",H27=""),"",I27/H27) -> 0.10244856
A28: HCLTech | B28: 45016 | C28: 101456 | D28: 14851 | E28: 93250 | F28: 543 | G28: 64862 | H28: 65405 | I28: 4794 | J28: 54.72602 | K28: 0.22706215 | L28: 0.28660369 | M28: =IF(OR(C28="",D28=""),"",D28/C28) -> 0.14637873 | N28: =IF(OR(D28="",E28=""),"",D28/E28) -> 0.15926005 | O28: =IF(OR(I28="",H28=""),"",I28/H28) -> 0.073297149
A29: HCLTech | B29: 45382 | C29: 109913 | D29: 15702 | E29: 99006 | F29: 543 | G29: 67720 | H29: 68263 | I29: 5756 | J29: 57.86196 | K29: 0.23002212 | L29: 0.29843709 | M29: =IF(OR(C29="",D29=""),"",D29/C29) -> 0.14285844 | N29: =IF(OR(D29="",E29=""),"",D29/E29) -> 0.15859645 | O29: =IF(OR(I29="",H29=""),"",I29/H29) -> 0.084320935
A30: HCLTech | B30: 45747 | C30: 117055 | D30: 17390 | E30: 104480 | F30: 543 | G30: 69112 | H30: 69655 | I30: 6276 | J30: 64.082249 | K30: 0.24965903 | L30: 0.31883961 | M30: =IF(OR(C30="",D30=""),"",D30/C30) -> 0.14856264 | N30: =IF(OR(D30="",E30=""),"",D30/E30) -> 0.16644334 | O30: =IF(OR(I30="",H30=""),"",I30/H30) -> 0.090101213
A31: HCLTech | B31: 46112 | C31: 130144 | D31: 16642 | E31: 116258 | F31: 543 | G31: 74622 | H31: 75165 | I31: 5215 | J31: 61.325865 | K31: 0.22140624 | L31: 0.29391406 | M31: =IF(OR(C31="",D31=""),"",D31/C31) -> 0.12787374 | N31: =IF(OR(D31="",E31=""),"",D31/E31) -> 0.14314714 | O31: =IF(OR(I31="",H31=""),"",I31/H31) -> 0.069380696
A32: Wipro | B32: 42825 | C32: 55448.4 | D32: 8493.1 | E32: 78672.2 | F32: 486.1 | G32: 51184.1 | H32: 51670.2 | I32: 14241.2 | J32: 6.5508916 | K32: 0.16437134 | M32: =IF(OR(C32="",D32=""),"",D32/C32) -> 0.15317124 | N32: =IF(OR(D32="",E32=""),"",D32/E32) -> 0.10795554 | O32: =IF(OR(I32="",H32=""),"",I32/H32) -> 0.27561728
A33: Wipro | B33: 43190 | C33: 54487.1 | D33: 8002.8 | E33: 75390.8 | F33: 904.8 | G33: 47021.5 | H33: 47926.3 | I33: 13901.2 | J33: 6.6338956 | K33: 0.16698139 | L33: 0.16948948 | M33: =IF(OR(C33="",D33=""),"",D33/C33) -> 0.14687513 | N33: =IF(OR(D33="",E33=""),"",D33/E33) -> 0.10615088 | O33: =IF(OR(I33="",H33=""),"",I33/H33) -> 0.29005369
A34: Wipro | B34: 43555 | C34: 59018.9 | D34: 9003.7 | E34: 82586.4 | F34: 1206.8 | G34: 55215.8 | H34: 56422.6 | I34: 9946.7 | J34: 7.4608673 | K34: 0.15957613 | L34: 0.19157576 | M34: =IF(OR(C34="",D34=""),"",D34/C34) -> 0.15255622 | N34: =IF(OR(D34="",E34=""),"",D34/E34) -> 0.10902158 | O34: =IF(OR(I34="",H34=""),"",I34/H34) -> 0.17628929
A35: Wipro | B35: 43921 | C35: 61137.6 | D35: 9722.3 | E35: 80999.6 | F35: 1142.7 | G35: 54179 | H35: 55321.7 | I35: 9724 | J35: 8.5084058 | K35: 0.17574116 | L35: 0.19761367 | M35: =IF(OR(C35="",D35=""),"",D35/C35) -> 0.15902325 | N35: =IF(OR(D35="",E35=""),"",D35/E35) -> 0.12002899 | O35: =IF(OR(I35="",H35=""),"",I35/H35) -> 0.17577189
A36: Wipro | B36: 44286 | C36: 61934.9 | D36: 10796.4 | E36: 82565.8 | F36: 1095.8 | G36: 53805.2 | H36: 54901 | I36: 10451.4 | J36: 9.8522581 | K36: 0.19665216 | L36: 0.22104156 | M36: =IF(OR(C36="",D36=""),"",D36/C36) -> 0.17431852 | N36: =IF(OR(D36="",E36=""),"",D36/E36) -> 0.13076116 | O36: =IF(OR(I36="",H36=""),"",I36/H36) -> 0.19036812
A37: Wipro | B37: 44651 | C37: 79312 | D37: 12229.6 | E37: 107275.6 | F37: 1096.4 | G37: 64306.6 | H37: 65403 | I37: 17592.9 | J37: 11.154222 | K37: 0.18698836 | L37: 0.21130407 | M37: =IF(OR(C37="",D37=""),"",D37/C37) -> 0.15419609 | N37: =IF(OR(D37="",E37=""),"",D37/E37) -> 0.11400169 | O37: =IF(OR(I37="",H37=""),"",I37/H37) -> 0.26899225
A38: Wipro | B38: 45016 | C38: 90487.6 | D38: 11350 | E38: 116923.7 | F38: 1097.6 | G38: 76570.3 | H38: 77667.9 | I38: 17466.6 | J38: 10.340932 | K38: 0.14613502 | L38: 0.17709947 | M38: =IF(OR(C38="",D38=""),"",D38/C38) -> 0.12543155 | N38: =IF(OR(D38="",E38=""),"",D38/E38) -> 0.097071851 | O38: =IF(OR(I38="",H38=""),"",I38/H38) -> 0.22488827
A39: Wipro | B39: 45382 | C39: 89760.3 | D39: 11045.2 | E39: 114608.9 | F39: 1045 | G39: 73488 | H39: 74533 | I39: 16464.9 | J39: 10.569266 | K39: 0.14819208 | L39: 0.1716649 | M39: =IF(OR(C39="",D39=""),"",D39/C39) -> 0.12305217 | N39: =IF(OR(D39="",E39=""),"",D39/E39) -> 0.096372969 | O39: =IF(OR(I39="",H39=""),"",I39/H39) -> 0.22090752
A40: Wipro | B40: 45747 | C40: 89088.4 | D40: 13135.4 | E40: 127929.1 | F40: 2094.4 | G40: 80269.7 | H40: 82364.1 | I40: 19203.5 | J40: 12.543234 | K40: 0.15947968 | L40: 0.19705191 | M40: =IF(OR(C40="",D40=""),"",D40/C40) -> 0.14744232 | N40: =IF(OR(D40="",E40=""),"",D40/E40) -> 0.10267719 | O40: =IF(OR(I40="",H40=""),"",I40/H40) -> 0.23315376
A41: Wipro | B41: 46112 | C41: 92624 | D41: 13197.4 | E41: 140883.5 | F41: 2097.7 | G41: 85920.6 | H41: 88018.3 | I41: 20291 | J41: 12.582853 | K41: 0.14993927 | L41: 0.17915168 | M41: =IF(OR(C41="",D41=""),"",D41/C41) -> 0.14248359 | N41: =IF(OR(D41="",E41=""),"",D41/E41) -> 0.093675981 | O41: =IF(OR(I41="",H41=""),"",I41/H41) -> 0.23053161
A42: Tech Mahindra | B42: 42825 | C42: 29140.8 | D42: 2812.9 | E42: 26057 | F42: 438.8 | G42: 15998.4 | H42: 16437.2 | I42: 1366.2 | J42: 28.876912 | K42: 0.17113012 | M42: =IF(OR(C42="",D42=""),"",D42/C42) -> 0.096527892 | N42: =IF(OR(D42="",E42=""),"",D42/E42) -> 0.1079518 | O42: =IF(OR(I42="",H42=""),"",I42/H42) -> 0.083116346
A43: Tech Mahindra | B43: 43190 | C43: 30772.9 | D43: 3799.8 | E43: 30431.4 | F43: 441.7 | G43: 18401.1 | H43: 18842.8 | I43: 2396.6 | J43: 38.785342 | K43: 0.20165793 | L43: 0.25823968 | M43: =IF(OR(C43="",D43=""),"",D43/C43) -> 0.12347878 | N43: =IF(OR(D43="",E43=""),"",D43/E43) -> 0.12486445 | O43: =IF(OR(I43="",H43=""),"",I43/H43) -> 0.12718917
A44: Tech Mahindra | B44: 43555 | C44: 34742.1 | D44: 4297.6 | E44: 33445.8 | F44: 443.7 | G44: 19840.7 | H44: 20284.4 | I44: 1995.5 | J44: 43.701444 | K44: 0.21186725 | L44: 0.26086817 | M44: =IF(OR(C44="",D44=""),"",D44/C44) -> 0.12370006 | N44: =IF(OR(D44="",E44=""),"",D44/E44) -> 0.12849446 | O44: =IF(OR(I44="",H44=""),"",I44/H44) -> 0.098376092
A45: Tech Mahindra | B45: 43921 | C45: 36867.7 | D45: 4033 | E45: 37317.9 | F45: 435.9 | G45: 21377.2 | H45: 21813.1 | I45: 3670.5 | J45: 41.753805 | K45: 0.1848889 | L45: 0.21982057 | M45: =IF(OR(C45="",D45=""),"",D45/C45) -> 0.10939115 | N45: =IF(OR(D45="",E45=""),"",D45/E45) -> 0.10807146 | O45: =IF(OR(I45="",H45=""),"",I45/H45) -> 0.16827044
A46: Tech Mahindra | B46: 44286 | C46: 37855.1 | D46: 4428 | E46: 39601.9 | F46: 437 | G46: 24428 | H46: 24865 | I46: 2900.8 | J46: 45.729629 | K46: 0.17808164 | L46: 0.2301209 | M46: =IF(OR(C46="",D46=""),"",D46/C46) -> 0.11697235 | N46: =IF(OR(D46="",E46=""),"",D46/E46) -> 0.11181282 | O46: =IF(OR(I46="",H46=""),"",I46/H46) -> 0.11666197
A47: Tech Mahindra | B47: 44651 | C47: 44646 | D47: 5566.1 | E47: 44415.5 | F47: 438.8 | G47: 26446.9 | H47: 26885.7 | I47: 2618.4 | J47: 57.276189 | K47: 0.20702827 | L47: 0.26592329 | M47: =IF(OR(C47="",D47=""),"",D47/C47) -> 0.12467186 | N47: =IF(OR(D47="",E47=""),"",D47/E47) -> 0.12531886 | O47: =IF(OR(I47="",H47=""),"",I47/H47) -> 0.097390062
A48: Tech Mahindra | B48: 45016 | C48: 53290.2 | D48: 4831.3 | E48: 45827.2 | F48: 440 | G48: 27484.5 | H48: 27924.5 | I48: 2740.2 | J48: 49.597577 | K48: 0.17301295 | L48: 0.22507014 | M48: =IF(OR(C48="",D48=""),"",D48/C48) -> 0.090660196 | N48: =IF(OR(D48="",E48=""),"",D48/E48) -> 0.10542429 | O48: =IF(OR(I48="",H48=""),"",I48/H48) -> 0.098128883
A49: Tech Mahindra | B49: 45382 | C49: 51995.5 | D49: 2357.8 | E49: 43149.1 | F49: 441.3 | G49: 26228.1 | H49: 26669.4 | I49: 2536.7 | J49: 24.138002 | K49: 0.088408438 | L49: 0.12081349 | M49: =IF(OR(C49="",D49=""),"",D49/C49) -> 0.045346232 | N49: =IF(OR(D49="",E49=""),"",D49/E49) -> 0.054643086 | O49: =IF(OR(I49="",H49=""),"",I49/H49) -> 0.095116501
A50: Tech Mahindra | B50: 45747 | C50: 52988.3 | D50: 4251.5 | E50: 44266.6 | F50: 442.4 | G50: 26919.1 | H50: 27361.5 | I50: 2025.2 | J50: 43.426966 | K50: 0.15538256 | L50: 0.20394656 | M50: =IF(OR(C50="",D50=""),"",D50/C50) -> 0.080234693 | N50: =IF(OR(D50="",E50=""),"",D50/E50) -> 0.096043066 | O50: =IF(OR(I50="",H50=""),"",I50/H50) -> 0.07401641
A51: Tech Mahindra | B51: 46112 | C51: 56815.4 | D51: 4810.9 | E51: 49167.7 | F51: 442.8 | G51: 29172.6 | H51: 29615.4 | I51: 2186.2 | J51: 49.100837 | K51: 0.16244589 | L51: 0.22587652 | M51: =IF(OR(C51="",D51=""),"",D51/C51) -> 0.084675986 | N51: =IF(OR(D51="",E51=""),"",D51/E51) -> 0.097846757 | O51: =IF(OR(I51="",H51=""),"",I51/H51) -> 0.073819702

Sheet TCS
A1: COMPANY NAME | B1: TATA CONSULTANCY SERVICES LTD | E1: =IF(B2<>B3, "A NEW VERSION OF THE WORKSHEET IS AVAILABLE", "")
A2: LATEST VERSION | B2: 2.1 | E2: PLEASE DO NOT MAKE ANY CHANGES TO THIS SHEET
A3: CURRENT VERSION | B3: 2.1
A5: META
A6: Number of shares | B6: =IF(B9>0, B9/B8, 0) -> 361.80875
A7: Face Value | B7: 1
A8: Current Price | B8: 2093.5
A9: Market Capitalization | B9: 757446.62
A15: PROFIT & LOSS
A16: Report Date | B16: 42825 | C16: 43190 | D16: 43555 | E16: 43921 | F16: 44286 | G16: 44651 | H16: 45016 | I16: 45382 | J16: 45747 | K16: 46112
A17: Sales | B17: 117966 | C17: 123104 | D17: 146463 | E17: 156949 | F17: 164177 | G17: 191754 | H17: 225458 | I17: 240893 | J17: 255324 | K17: 267021
A18: Raw Material Cost | B18: 94 | C18: 86 | D18: 40 | E18: 18 | F18: 14 | G18: 29 | H18: 37 | I18: 42 | J18: 49 | K18: 43
A19: Change in Inventory | B19: 1
A20: Power and Fuel
A21: Other Mfr. Exp | B21: 2715 | C21: 2614 | D21: 2230 | E21: 1887 | F21: 1448 | G21: 1134 | H21: 1844 | I21: 3660 | J21: 11599 | K21: 4356
A22: Employee Cost | B22: 61621 | C22: 66396 | D22: 78246 | E22: 85952 | F22: 91814 | G22: 107554 | H22: 127522 | I22: 140131 | J22: 145788 | K22: 154994
A23: Selling and admin | B23: 16392 | C23: 16808 | D23: 20387 | E23: 20527 | F23: 18322 | G23: 23187 | H23: 28913 | I23: 24151 | J23: 20729 | K23: 24434
A24: Other Expenses | B24: 4834 | C24: 4684 | D24: 6054 | E24: 6456 | F24: 6033 | G24: 6793 | H24: 7883 | I24: 8613 | J24: 9752 | K24: 10796
A25: Other Income | B25: 4221 | C25: 3642 | D25: 4311 | E25: 4592 | F25: 1916 | G25: 4018 | H25: 3449 | I25: 3464 | J25: 3962 | K25: -124
A26: Depreciation | B26: 1987 | C26: 2014 | D26: 2056 | E26: 3529 | F26: 4065 | G26: 4604 | H26: 5022 | I26: 4985 | J26: 5242 | K26: 5560
A27: Interest | B27: 32 | C27: 52 | D27: 198 | E27: 924 | F27: 637 | G27: 784 | H27: 779 | I27: 778 | J27: 796 | K27: 1227
A28: Profit before tax | B28: 34513 | C28: 34092 | D28: 41563 | E28: 42248 | F28: 43760 | G28: 51687 | H28: 56907 | I28: 61997 | J28: 65331 | K28: 65487
A29: Tax | B29: 8156 | C29: 8212 | D29: 10001 | E29: 9801 | F29: 11198 | G29: 13238 | H29: 14604 | I29: 15898 | J29: 16534 | K29: 16033
A30: Net profit | B30: 26289 | C30: 25826 | D30: 31472 | E30: 32340 | F30: 32430 | G30: 38327 | H30: 42147 | I30: 45908 | J30: 48553 | K30: 49210
A31: Dividend Amount | B31: 9259 | C31: 9550 | D31: 11250 | E31: 27375 | F31: 14060 | G31: 15738 | H31: 42090 | I31: 26426 | J31: 45612 | K31: 39820
A32: EPS | B32: 66.708112 | C32: 67.455467 | D32: 83.871655 | E32: 86.184842 | F32: 87.669974 | G32: 104.74434 | H32: 115.18406 | I32: 126.88428 | J32: 134.19474 | K32: 136.01061
A40: Quarters
A41: Report Date | B41: 45291 | C41: 45382 | D41: 45473 | E41: 45565 | F41: 45657 | G41: 45747 | H41: 45838 | I41: 45930 | J41: 46022 | K41: 46112
A42: Sales | B42: 60583 | C42: 61237 | D42: 62613 | E42: 64259 | F42: =TechM!B61 -> 26057 | G42: 64479 | H42: 63437 | I42: 65799 | J42: 67087 | K42: 70698
A43: Expenses | B43: 44195 | C43: 44073 | D43: 45951 | E43: 47528 | F43: =TechM!C61 -> 30431.4 | G43: 47499 | H43: 46562 | I43: 47821 | J43: 48818 | K43: 51422
A44: Other Income | B44: -96 | C44: 1157 | D44: 962 | E44: 729 | F44: =TechM!D61 -> 33445.8 | G44: 1028 | H44: 1660 | I44: -268 | J44: -2273 | K44: 757
A45: Depreciation | B45: 1233 | C45: 1246 | D45: 1220 | E45: 1266 | F45: =TechM!E61 -> 37317.9 | G45: 1379 | H45: 1361 | I45: 1413 | J45: 1380 | K45: 1406
A46: Interest | B46: 230 | C46: 226 | D46: 173 | E46: 162 | F46: =TechM!F61 -> 39601.9 | G46: 227 | H46: 195 | I46: 229 | J46: 538 | K46: 265
A47: Profit before tax | B47: 14829 | C47: 16849 | D47: 16231 | E47: 16032 | F47: =TechM!G61 -> 44415.5 | G47: 16402 | H47: 16979 | I47: 16068 | J47: 14078 | K47: 18362
A48: Tax | B48: 3732 | C48: 4347 | D48: 4126 | E48: 4077 | F48: =TechM!H61 -> 45827.2 | G48: 4109 | H48: 4160 | I48: 3937 | J48: 3358 | K48: 4578
A49: Net profit | B49: 11058 | C49: 12434 | D49: 12040 | E49: 11909 | F49: =TechM!I61 -> 43149.1 | G49: 12224 | H49: 12760 | I49: 12075 | J49: 10657 | K49: 13718
A50: Operating Profit | B50: 16388 | C50: 17164 | D50: 16662 | E50: 16731 | F50: =TechM!J61 -> 44266.6 | G50: 16980 | H50: 16875 | I50: 17978 | J50: 18269 | K50: 19276
F51: =TechM!K61 -> 49167.7
A55: BALANCE SHEET
A56: Report Date | B56: 42825 | C56: 43190 | D56: 43555 | E56: 43921 | F56: 44286 | G56: 44651 | H56: 45016 | I56: 45382 | J56: 45747 | K56: 46112
A57: Equity Share Capital | B57: 197 | C57: 191 | D57: 375 | E57: 375 | F57: 370 | G57: 366 | H57: 366 | I57: 362 | J57: 362 | K57: 362
A58: Reserves | B58: 86017 | C58: 84937 | D58: 89071 | E58: 83751 | F58: 86063 | G58: 88773 | H58: 90058 | I58: 90127 | J58: 94394 | K58: 106878
A59: Borrowings | B59: 289 | C59: 247 | D59: 62 | E59: 8174 | F59: 7795 | G59: 7818 | H59: 7688 | I59: 8021 | J59: 9392 | K59: 11283
A60: Other Liabilities | B60: 15830 | C60: 19751 | D60: 24393 | E60: 27827 | F60: 35764 | G60: 43967 | H60: 44747 | I60: 46962 | J60: 54501 | K60: 62644
A61: Total | B61: 102333 | C61: 105126 | D61: 113901 | E61: 120127 | F61: 129992 | G61: 140924 | H61: 142859 | I61: 145472 | J61: 158649 | K61: 181167
A62: Net Block | B62: 11701 | C62: 11973 | D62: 12290 | E62: 20928 | F62: 21021 | G62: 21298 | H62: 20515 | I62: 19604 | J62: 23053 | K62: 31343
A63: Capital Work in Progress | B63: 1541 | C63: 1278 | D63: 963 | E63: 906 | F63: 926 | G63: 1205 | H63: 1234 | I63: 1564 | J63: 1546 | K63: 2665
A64: Investments | B64: 41980 | C64: 36008 | D64: 29330 | E64: 26356 | F64: 29373 | G64: 30485 | H64: 37163 | I64: 31762 | J64: 30964 | K64: 33988
A65: Other Assets | B65: 47111 | C65: 55867 | D65: 71318 | E65: 71937 | F65: 78672 | G65: 87936 | H65: 83947 | I65: 92542 | J65: 103086 | K65: 113171
A66: Total | B66: 102333 | C66: 105126 | D66: 113901 | E66: 120127 | F66: 129992 | G66: 140924 | H66: 142859 | I66: 145472 | J66: 158649 | K66: 181167
A67: Receivables | B67: 22617 | C67: 24943 | D67: 27346 | E67: 30532 | F67: 30079 | G67: 41810 | H67: 49954 | I67: 53577 | J67: 59046 | K67: 67714
... A70: No. of Equity Shares | B70: 1970427941 | C70: 1914287591 | D70: 3752384706 | E70: 3752384706 | F70: 3699051373 | G70: 3659051373 | H70: 3659051373 | I70: 3618087518 | J70: 3618087518 | K70: 3618087518
A71: New Bonus Shares
A72: Face value | B72: 1 | C72: 1 | D72: 1 | E72: 1 | F72: 1 | G72: 1 | H72: 1 | I72: 1 | J72: 1 | K72: 1
A73: Return on Equity | B73: 0.30492727 | C73: 0.30337844 | D73: 0.35185475 | E73: 0.38442336 | F73: 0.37520392 | G73: 0.42996892 | H73: 0.46610413 | I73: 0.50733238 | J73: 0.51240027 | K73: 0.45887728
A74: Return on Capital Emp | C74: 0.39730507 | D74: 0.47758787 | E74: 0.4749186 | F74: 0.47603577 | G74: 0.5489029 | H74: 0.591442 | I74: 0.63853485 | J74: 0.65259699 | K74: 0.59921588
A80: CASH FLOW:
A81: Report Date | B81: 42825 | C81: 43190 | D81: 43555 | E81: 43921 | F81: 44286 | G81: 44651 | H81: 45016 | I81: 45382 | J81: 45747 | K81: 46112
A82: Cash from Operating Activity | B82: 25223 | C82: 25067 | D82: 28593 | E82: 32369 | F82: 38802 | G82: 39949 | H82: 41965 | I82: 44338 | J82: 48908 | K82: 52094
A83: Cash from Investing Activity | B83: -16895 | C83: 3104 | D83: 1645 | E83: 8968 | F83: -7956 | G83: -738 | H83: 548 | I83: 6091 | J83: -2144 | K83: -11886
A84: Cash from Financing Activity | B84: -11026 | C84: -26885 | D84: -27897 | E84: -39915 | F84: -32634 | G84: -33581 | H84: -47878 | I84: -48536 | J84: -47438 | K84: -42133
A85: Net Cash Flow | B85: -2698 | C85: 1286 | D85: 2341 | E85: 1422 | F85: -1788 | G85: 5630 | H85: -5365 | I85: 1893 | J85: -674 | K85: -1925
A90: PRICE: | B90: 1215.9 | C90: 1424.58 | D90: 2001.65 | E90: 1826.1 | F90: 3177.85 | G90: 3739.95 | H90: 3205.9 | I90: 3876.3 | J90: 3606.15 | K90: 2358.9
A92: DERIVED:
A93: Adjusted Equity Shares in Cr | B93: 394.09 | C93: 382.86 | D93: 375.24 | E93: 375.24 | F93: 369.91 | G93: 365.91 | H93: 365.91 | I93: 361.81 | J93: 361.81 | K93: 361.81

Sheet Infosys
A1: COMPANY NAME | B1: INFOSYS LTD | E1: =IF(B2<>B3, "A NEW VERSION OF THE WORKSHEET IS AVAILABLE", "")
A2: LATEST VERSION | B2: 2.1 | E2: PLEASE DO NOT MAKE ANY CHANGES TO THIS SHEET
A3: CURRENT VERSION | B3: 2.1
A5: META
A6: Number of shares | B6: =IF(B9>0, B9/B8, 0) -> 405.75789
A7: Face Value | B7: 5
A8: Current Price | B8: 1047.2
A9: Market Capitalization | B9: 424909.66
A15: PROFIT & LOSS
A16: Report Date | B16: 42825 | C16: 43190 | D16: 43555 | E16: 43921 | F16: 44286 | G16: 44651 | H16: 45016 | I16: 45382 | J16: 45747 | K16: 46112
A17: Sales | B17: 68484 | C17: 70522 | D17: 82675 | E17: 90791 | F17: 100472 | G17: 121641 | H17: 146767 | I17: 153670 | J17: 162990 | K17: 178650
A18: Raw Material Cost
A19: Change in Inventory
A20: Power and Fuel | B20: 228 | C20: 207 | D20: 221 | E20: 229 | F20: 143 | G20: 132 | H20: 176 | I20: 199 | J20: 222 | K20: 223
A21: Other Mfr. Exp | B21: 6712 | C21: 7286 | D21: 9902 | E21: 11086 | F21: 12800 | G21: 20690 | H21: 26330 | I21: 27195 | J21: 30395 | K21: 32922
A22: Employee Cost | B22: 37669 | C22: 38902 | D22: 45323 | E22: 50895 | F22: 55547 | G22: 63997 | H22: 78374 | I22: 82636 | J22: 85968 | K22: 95112
A23: Selling and admin | B23: 4584 | C23: 4585 | D23: 5553 | E23: 5375 | F23: 3194 | G23: 4305 | H23: 5300 | I23: 5705 | J23: 6039 | K23: 6784
A24: Other Expenses | B24: 687 | C24: 720 | D24: 1506 | E24: 939 | F24: 899 | G24: 1026 | H24: 1457 | I24: 1510 | J24: 1130 | K24: 1329
A25: Other Income | B25: 3050 | C25: 3311 | D25: 2882 | E25: 2803 | F25: 2201 | G25: 2295 | H25: 2701 | I25: 4711 | J25: 3600 | K25: 3033
A26: Depreciation | B26: 1703 | C26: 1863 | D26: 2011 | E26: 2893 | F26: 3267 | G26: 3476 | H26: 4225 | I26: 4678 | J26: 4812 | K26: 4902
A27: Interest | E27: 170 | F27: 195 | G27: 200 | H27: 284 | I27: 470 | J27: 416 | K27: 416
A28: Profit before tax | B28: 19951 | C28: 20270 | D28: 21041 | E28: 22007 | F28: 26628 | G28: 30110 | H28: 33322 | I28: 35988 | J28: 37608 | K28: 39995
A29: Tax | B29: 5598 | C29: 4241 | D29: 5631 | E29: 5368 | F29: 7205 | G29: 7964 | H29: 9214 | I29: 9740 | J29: 10858 | K29: 10521
A30: Net profit | B30: 14353 | C30: 16029 | D30: 15404 | E30: 16594 | F30: 19351 | G30: 22110 | H30: 24095 | I30: 26233 | J30: 26713 | K30: 29440
A31: Dividend Amount | B31: 5891.6 | C31: 9465.6 | D31: 9222.5 | E31: 7427 | F31: 11469.6 | G31: 13007.6 | H31: 14069.2 | I31: 19053.2 | J31: 17827.8 | K31: 19430.4
A32: EPS | B32: 31.243606 | C32: 36.694748 | D32: 35.258303 | E32: 38.962198 | F32: 45.41742 | G32: 52.559013 | H32: 58.079834 | I32: 63.198343 | J32: 64.317531 | K32: 72.590985
A40: Quarters
A41: Report Date | B41: 45291 | C41: 45382 | D41: 45473 | E41: 45565 | F41: 45657 | G41: 45747 | H41: 45838 | I41: 45930 | J41: 46022 | K41: 46112
A42: Sales | B42: 38821 | C42: 37923 | D42: 39315 | E42: 40986 | F42: 41764 | G42: 40925 | H42: 42279 | I42: 44490 | J42: 45479 | K42: 46402
A43: Expenses | B43: 29684 | C43: 29139 | D43: 29878 | E43: 31177 | F43: 31649 | G43: 31051 | H43: 32336 | I43: 33955 | J43: 34845 | K43: 35235
A44: Other Income | B44: 789 | C44: 2729 | D44: 838 | E44: 712 | F44: 859 | G44: 1190 | H44: 1042 | I44: 982 | J44: -150 | K44: 1159
A45: Depreciation | B45: 1176 | C45: 1163 | D45: 1149 | E45: 1160 | F45: 1203 | G45: 1299 | H45: 1140 | I45: 1182 | J45: 1155 | K45: 1424
A46: Interest | B46: 131 | C46: 110 | D46: 105 | E46: 108 | F46: 101 | G46: 102 | H46: 105 | I46: 106 | J46: 100 | K46: 105
A47: Profit before tax | B47: 8619 | C47: 10240 | D47: 9021 | E47: 9253 | F47: 9670 | G47: 9663 | H47: 9740 | I47: 10229 | J47: 9229 | K47: 10797
A48: Tax | B48: 2506 | C48: 2265 | D48: 2647 | E48: 2737 | F48: 2848 | G48: 2625 | H48: 2816 | I48: 2854 | J48: 2563 | K48: 2288
A49: Net profit | B49: 6106 | C49: 7969 | D49: 6368 | E49: 6506 | F49: 6806 | G49: 7033 | H49: 6921 | I49: 7364 | J49: 6654 | K49: 8501
A50: Operating Profit | B50: 9137 | C50: 8784 | D50: 9437 | E50: 9809 | F50: 10115 | G50: 9874 | H50: 9943 | I50: 10535 | J50: 10634 | K50: 11167
A55: BALANCE SHEET
A56: Report Date | B56: 42825 | C56: 43190 | D56: 43555 | E56: 43921 | F56: 44286 | G56: 44651 | H56: 45016 | I56: 45382 | J56: 45747 | K56: 46112
A57: Equity Share Capital | B57: 1144 | C57: 1088 | D57: 2170 | E57: 2122 | F57: 2124 | G57: 2098 | H57: 2069 | I57: 2071 | J57: 2073 | K57: 2024
A58: Reserves | B58: 67838 | C58: 63835 | D58: 62778 | E58: 63328 | F58: 74227 | G58: 73252 | H58: 73338 | I58: 86045 | J58: 93745 | K58: 90828
A59: Borrowings | E59: 4633 | F59: 5325 | G59: 5474 | H59: 8299 | I59: 8359 | J59: 8227 | K59: 9176
A60: Other Liabilities | B60: 14166 | C60: 14426 | D60: 19118 | E60: 21717 | F60: 25835 | G60: 35905 | H60: 40890 | I60: 39545 | J60: 43750 | K60: 52260
A61: Total | B61: 83148 | C61: 79349 | D61: 84066 | E61: 91800 | F61: 107511 | G61: 116729 | H61: 124596 | I61: 136020 | J61: 147795 | K61: 154288
A62: Net Block | B62: 14179 | C62: 12574 | D62: 15710 | E62: 23789 | F62: 25505 | G62: 25800 | H62: 29225 | I62: 27622 | J62: 30961 | K62: 33770
A63: Capital Work in Progress | B63: 1365 | C63: 1606 | D63: 1388 | E63: 954 | F63: 922 | G63: 416 | H63: 288 | I63: 293 | J63: 814 | K63: 526
A64: Investments | B64: 16423 | C64: 12163 | D64: 11261 | E64: 8792 | F64: 14205 | G64: 20324 | H64: 19478 | I64: 24623 | J64: 23541 | K64: 21880
A65: Other Assets | B65: 51181 | C65: 53006 | D65: 55707 | E65: 58265 | F65: 66879 | G65: 70189 | H65: 75605 | I65: 83482 | J65: 92479 | K65: 98112
A66: Total | B66: 83148 | C66: 79349 | D66: 84066 | E66: 91800 | F66: 107511 | G66: 116729 | H66: 124596 | I66: 136020 | J66: 147795 | K66: 154288
A67: Receivables | B67: 12322 | C67: 13142 | D67: 14827 | E67: 18487 | F67: 19294 | G67: 22698 | H67: 25424 | I67: 30193 | J67: 31158 | K67: 35234
A68: Inventory
A69: Cash & Bank | B69: 22625 | C69: 19818 | D69: 19568 | E69: 18649 | F69: 24714 | G69: 17472 | H69: 12173 | I69: 14786 | J69: 24455 | K69: 22201
A70: No. of Equity Shares | B70: 2285655150 | C70: 2173312301 | D70: 4335954462 | E70: 4240753210 | F70: 4245146114 | G70: 4193012929 | H70: 4136387925 | I70: 4139950635 | J70: 4143607528 | K70: 4046940812
A71: New Bonus Shares | D71: 2184191490
A72: Face value | B72: 5 | C72: 5 | D72: 5 | E72: 5 | F72: 5 | G72: 5 | H72: 5 | I72: 5 | J72: 5 | K72: 5
A73: Return on Equity | B73: 0.20806877 | C73: 0.24689247 | D73: 0.23717435 | E73: 0.25353705 | F73: 0.25344789 | G73: 0.29343066 | H73: 0.31953267 | I73: 0.29770984 | J73: 0.27878895 | K73: 0.31706371
A74: Return on Capital Emp | C74: 0.30275195 | D74: 0.32402923 | E74: 0.32847272 | F74: 0.35349469 | G74: 0.37304615 | H74: 0.40850909 | I74: 0.40468196 | J74: 0.37925394 | K74: 0.39220082
A80: CASH FLOW:
A81: Report Date | B81: 42825 | C81: 43190 | D81: 43555 | E81: 43921 | F81: 44286 | G81: 44651 | H81: 45016 | I81: 45382 | J81: 45747 | K81: 46112
A82: Cash from Operating Activity | B82: 11531 | C82: 13218 | D82: 14841 | E82: 17003 | F82: 23224 | G82: 23885 | H82: 22467 | I82: 25210 | J82: 35694 | K82: 33986
A83: Cash from Investing Activity | B83: -14664 | C83: 4533 | D83: -632 | E83: -331 | F83: -7373 | G83: -6485 | H83: -1071 | I83: -5093 | J83: -1864 | K83: 3546
A84: Cash from Financing Activity | B84: -6939 | C84: -20505 | D84: -14512 | E84: -17591 | F84: -9786 | G84: -24642 | H84: -26695 | I84: -17504 | J84: -24161 | K84: -39786
A85: Net Cash Flow | B85: -10072 | C85: -2754 | D85: -303 | E85: -919 | F85: 6065 | G85: -7242 | H85: -5299 | I85: 2613 | J85: 9669 | K85: -2254
A90: PRICE: | B90: 511.13 | C90: 565.9 | D90: 743.85 | E90: 641.5 | F90: 1368.05 | G90: 1906.85 | H90: 1427.95 | I90: 1498.05 | J90: 1570.65 | K90: 1250.6
A92: DERIVED:
A93: Adjusted Equity Shares in Cr | B93: 459.39 | C93: 436.82 | D93: 436.89 | E93: 425.9 | F93: 426.07 | G93: 420.67 | H93: 414.86 | I93: 415.09 | J93: 415.33 | K93: 405.56

Sheet HCLTech
A1: COMPANY NAME | B1: HCL TECHNOLOGIES LTD | E1: =IF(B2<>B3, "A NEW VERSION OF THE WORKSHEET IS AVAILABLE", "")
A2: LATEST VERSION | B2: 2.1 | E2: PLEASE DO NOT MAKE ANY CHANGES TO THIS SHEET
A3: CURRENT VERSION | B3: 2.1
A5: META
A6: Number of shares | B6: =IF(B9>0, B9/B8, 0) -> 271.36651
A7: Face Value | B7: 2
A8: Current Price | B8: 1139
A9: Market Capitalization | B9: 309086.45
A15: PROFIT & LOSS
A16: Report Date | B16: 42825 | C16: 43190 | D16: 43555 | E16: 43921 | F16: 44286 | G16: 44651 | H16: 45016 | I16: 45382 | J16: 45747 | K16: 46112
A17: Sales | B17: 47568 | C17: 50569 | D17: 60427 | E17: 70676 | F17: 75379 | G17: 85651 | H17: 101456 | I17: 109913 | J17: 117055 | K17: 130144
A18: Raw Material Cost | B18: 826 | C18: 1251 | D18: 1615 | E18: 1536 | F18: 1698 | G18: 1473 | H18: 2072 | I18: 1754 | J18: 1976 | K18: 2715
A19: Change in Inventory | B19: 11 | C19: -104 | D19: -81 | F19: 3 | G19: 67 | H19: 67 | I19: -43 | J19: -52 | K19: 106
A20: Power and Fuel | B20: 307 | C20: 313 | D20: 336 | E20: 307 | F20: 275 | G20: 291 | H20: 328 | I20: 360 | J20: 355
A21: Other Mfr. Exp | B21: 9286 | C21: 9388 | D21: 10862 | E21: 12324 | F21: 12084 | G21: 14574 | H21: 17303 | I21: 15651 | J21: 16276
A22: Employee Cost | B22: 22866 | C22: 24729 | D22: 29283 | E22: 34928 | F22: 38853 | G22: 46130 | H22: 55280 | I22: 62480 | J22: 66755 | K22: 74143
A23: Selling and admin | B23: 2988 | C23: 2810 | D23: 3519 | E23: 3050 | F23: 1681 | G23: 1866 | H23: 2687 | I23: 3858 | J23: 4504
A24: Other Expenses | B24: 916 | C24: 728 | D24: 805 | E24: 1215 | F24: 743 | G24: 855 | H24: 1225 | I24: 1569 | J24: 1633 | K24: 26640
A25: Other Income | B25: 1069 | C25: 1230 | D25: 943 | E25: 589 | F25: 927 | G25: 1067 | H25: 1358 | I25: 1495 | J25: 2485 | K25: 574
A26: Depreciation | B26: 828 | C26: 1383 | D26: 2073 | E26: 3420 | F26: 4611 | G26: 4326 | H26: 4145 | I26: 4173 | J26: 4084 | K26: 4355
A27: Interest | B27: 89 | C27: 69 | D27: 174 | E27: 505 | F27: 511 | G27: 319 | H27: 353 | I27: 553 | J27: 644 | K27: 869
A28: Profit before tax | B28: 10542 | C28: 11024 | D28: 12622 | E28: 13980 | F28: 15853 | G28: 16951 | H28: 19488 | I28: 20967 | J28: 23261 | K28: 22102
A29: Tax | B29: 1936 | C29: 2302 | D29: 2502 | E29: 2923 | F29: 4684 | G29: 3428 | H29: 4643 | I29: 5257 | J29: 5862 | K29: 5450
A30: Net profit | B30: 8606 | C30: 8721 | D30: 10120 | E30: 11057 | F30: 11145 | G30: 13499 | H30: 14851 | I30: 15702 | J30: 17390 | K30: 16642
A31: Dividend Amount | B31: 3420 | C31: 1668 | D31: 1084 | E31: 2715 | F31: 2715 | G31: 11403 | H31: 13032 | I31: 14118 | J31: 16290 | K31: 14661
A32: EPS | B32: 30.158396 | C32: 31.319806 | D32: 37.30738 | E32: 40.745108 | F32: 41.069389 | G32: 49.743892 | H32: 54.72602 | I32: 57.86196 | J32: 64.082249 | K32: 61.325865
A40: Quarters
A41: Report Date | B41: 45291 | C41: 45382 | D41: 45473 | E41: 45565 | F41: 45657 | G41: 45747 | H41: 45838 | I41: 45930 | J41: 46022 | K41: 46112
A42: Sales | B42: 28446 | C42: 28499 | D42: 28057 | E42: 28862 | F42: 29890 | G42: 30246 | H42: 30349 | I42: 31942 | J42: 33872 | K42: 33981
A43: Expenses | B43: 21659 | C43: 22382 | D43: 22264 | E43: 22493 | F43: 23030 | G43: 23764 | H43: 24314 | I43: 25397 | J43: 26460 | K43: 27269
A44: Other Income | B44: 370 | C44: 416 | D44: 1103 | E44: 456 | F44: 477 | G44: 449 | H44: 456 | I44: 415 | J44: -571 | K44: 322
A45: Depreciation | B45: 1143 | C45: 1093 | D45: 998 | E45: 1007 | F45: 1039 | G45: 1040 | H45: 1093 | I45: 1043 | J45: 1127 | K45: 1092
A46: Interest | B46: 140 | C46: 171 | D46: 191 | E46: 131 | F46: 166 | G46: 156 | H46: 209 | I46: 215 | J46: 205 | K46: 240
A47: Profit before tax | B47: 5874 | C47: 5269 | D47: 5707 | E47: 5687 | F47: 6132 | G47: 5735 | H47: 5189 | I47: 5702 | J47: 5509 | K47: 5702
A48: Tax | B48: 1523 | C48: 1274 | D48: 1448 | E48: 1450 | F48: 1538 | G48: 1426 | H48: 1345 | I48: 1466 | J48: 1427 | K48: 1212
A49: Net profit | B49: 4350 | C49: 3986 | D49: 4257 | E49: 4235 | F49: 4591 | G49: 4307 | H49: 3843 | I49: 4235 | J49: 4076 | K49: 4488
A50: Operating Profit | B50: 6787 | C50: 6117 | D50: 5793 | E50: 6369 | F50: 6860 | G50: 6482 | H50: 6035 | I50: 6545 | J50: 7412 | K50: 6712
A55: BALANCE SHEET
A56: Report Date | B56: 42825 | C56: 43190 | D56: 43555 | E56: 43921 | F56: 44286 | G56: 44651 | H56: 45016 | I56: 45382 | J56: 45747 | K56: 46112
A57: Equity Share Capital | B57: 285 | C57: 278 | D57: 271 | E57: 543 | F57: 543 | G57: 543 | H57: 543 | I57: 543 | J57: 543 | K57: 543
A58: Reserves | B58: 32664 | C58: 36108 | D58: 41095 | E58: 50724 | F58: 59370 | G58: 61371 | H58: 64862 | I58: 67720 | J58: 69112 | K58: 74622
A59: Borrowings | B59: 582 | C59: 557 | D59: 4195 | E59: 7986 | F59: 6864 | G59: 6343 | H59: 4794 | I59: 5756 | J59: 6276 | K59: 5215
A60: Other Liabilities | B60: 12231 | C60: 11046 | D60: 12788 | E60: 23566 | F60: 19270 | G60: 20664 | H60: 23051 | I60: 24987 | J60: 28549 | K60: 35878
A61: Total | B61: 45762 | C61: 47989 | D61: 58349 | E61: 82819 | F61: 86047 | G61: 88921 | H61: 93250 | I61: 99006 | J61: 104480 | K61: 116258
A62: Net Block | B62: 15235 | C62: 18753 | D62: 22888 | E62: 37490 | F62: 37145 | G62: 35077 | H62: 34619 | I62: 35063 | J62: 36172 | K62: 37379
A63: Capital Work in Progress | B63: 448 | C63: 320 | D63: 235 | E63: 400 | F63: 312 | G63: 129 | H63: 40 | I63: 108 | J63: 59 | K63: 60
A64: Investments | B64: 1306 | C64: 2660 | D64: 2305 | E64: 7066 | F64: 6862 | G64: 6351 | H64: 5495 | I64: 7137 | J64: 7564 | K64: 7090
A65: Other Assets | B65: 28773 | C65: 26256 | D65: 32921 | E65: 37863 | F65: 41728 | G65: 47364 | H65: 53096 | I65: 56698 | J65: 60685 | K65: 71729
A66: Total | B66: 45762 | C66: 47989 | D66: 58349 | E66: 82819 | F66: 86047 | G66: 88921 | H66: 93250 | I66: 99006 | J66: 104480 | K66: 116258
A67: Receivables | B67: 8301 | C67: 9639 | D67: 11706 | E67: 14131 | F67: 17525 | G67: 20671 | H67: 25506 | I67: 25521 | J67: 25842 | K67: 23585
... A69: Cash & Bank | B69: 9044 | C69: 4018 | D69: 7872 | E69: 4976 | F69: 8888 | G69: 12636 | H69: 14724 | I69: 20150 | J69: 21289 | K69: 23425
A70: No. of Equity Shares | B70: 1426783424 | C70: 1392246384 | D70: 1356278868 | E70: 2713665096 | F70: 2713665096 | G70: 2713665096 | H70: 2713665096 | I70: 2713665096 | J70: 2713665096
A71: New Bonus Shares
A72: Face value | B72: 2 | C72: 2 | D72: 2 | E72: 2 | F72: 2 | G72: 2 | H72: 2 | I72: 2 | J72: 2 | K72: 2
A73: Return on Equity | B73: 0.26119154 | C73: 0.2396801 | D73: 0.24464536 | E73: 0.2156748 | F73: 0.18601973 | G73: 0.21802823 | H73: 0.22706215 | I73: 0.23002212 | J73: 0.24965903 | K73: 0.22140624
A74: Return on Capital Emp | C74: 0.31481114 | D74: 0.31019102 | E74: 0.27639437 | F74: 0.2596842 | G74: 0.25578743 | H74: 0.28660369 | I74: 0.29843709 | J74: 0.31883961 | K74: 0.29391406
A80: CASH FLOW:
A81: Report Date | B81: 42825 | C81: 43190 | D81: 43555 | E81: 43921 | F81: 44286 | G81: 44651 | H81: 45016 | I81: 45382 | J81: 45747 | K81: 46112
A82: Cash from Operating Activity | B82: 8995 | C82: 8328 | D82: 8971 | E82: 13359 | F82: 19618 | G82: 16900 | H82: 18009 | I82: 22448 | J82: 22261 | K82: 19975
A83: Cash from Investing Activity | B83: -3890 | C83: -2236 | D83: -3256 | E83: -12332 | F83: -5665 | G83: 1597 | H83: -3573 | I83: -6608 | J83: -4896 | K83: -1473
A84: Cash from Financing Activity | B84: -4517 | C84: -5714 | D84: -1471 | E84: -3168 | F84: -11192 | G84: -14508 | H84: -15881 | I84: -15464 | J84: -18561 | K84: -19369
A85: Net Cash Flow | B85: 588 | C85: 378 | D85: 4244 | E85: -2141 | F85: 2761 | G85: 3989 | H85: -1445 | I85: 376 | J85: -1196 | K85: -867
A90: PRICE: | B90: 437.38 | C90: 484.3 | D90: 543.73 | E90: 436.4 | F90: 982.65 | G90: 1163.75 | H90: 1085.25 | I90: 1543.55 | J90: 1592.5 | K90: 1341.6
A92: DERIVED:
A93: Adjusted Equity Shares in Cr | B93: 285.36 | C93: 278.45 | D93: 271.26 | E93: 271.37 | F93: 271.37 | G93: 271.37 | H93: 271.37 | I93: 271.37 | J93: 271.37 | K93: 271.37

Sheet Wipro
A1: COMPANY NAME | B1: WIPRO LTD | E1: =IF(B2<>B3, "A NEW VERSION OF THE WORKSHEET IS AVAILABLE", "")
A2: LATEST VERSION | B2: 2.1 | E2: PLEASE DO NOT MAKE ANY CHANGES TO THIS SHEET
A3: CURRENT VERSION | B3: 2.1
A5: META
A6: Number of shares | B6: =IF(B9>0, B9/B8, 0) -> 990.35495
A7: Face Value | B7: 2
A8: Current Price | B8: 176.08
A9: Market Capitalization | B9: 174381.7
A15: PROFIT & LOSS
A16: Report Date | B16: 42825 | C16: 43190 | D16: 43555 | E16: 43921 | F16: 44286 | G16: 44651 | H16: 45016 | I16: 45382 | J16: 45747 | K16: 46112
A17: Sales | B17: 55448.4 | C17: 54487.1 | D17: 59018.9 | E17: 61137.6 | F17: 61934.9 | G17: 79312 | H17: 90487.6 | I17: 89760.3 | J17: 89088.4 | K17: 92624
A18: Raw Material Cost | B18: 2556 | C18: 1843.4 | D18: 1407.3 | E18: 936 | F18: 695.7 | G18: 673.5 | H18: 649.4 | I18: 383.2 | J18: 296.7 | K18: 575.5
A19: Change in Inventory | B19: -141.1 | C19: -50.5 | D19: 67.3 | E19: -202.2 | F19: -31.5 | G19: 36.9 | H19: -15 | I19: -27.8 | J19: -19.5 | K19: -17.1
A20: Power and Fuel
A21: Other Mfr. Exp | G21: 1327.9 | H21: 1871.7 | I21: 1837.8 | J21: 1933.8 | K21: 2172
A22: Employee Cost | B22: 26808.1 | C22: 27222.3 | D22: 29977.4 | E22: 32657.1 | F22: 33237.1 | G22: 45007.5 | H22: 53764.4 | I22: 54930.1 | J22: 53347.7 | K22: 55585.5
A23: Selling and admin | B23: 13775.7 | C23: 13853.3 | D23: 14796.3 | E23: 14350.4 | F23: 12523.8 | G23: 15524.3 | H23: 17123.9 | I23: 15667.3 | J23: 15481.7 | K23: 16038.7
A24: Other Expenses | B24: 846.6 | C24: 1130.5 | D24: 1292.6 | E24: 649.6 | F24: 675.4 | G24: 131.5 | H24: 224.2 | I24: 161.6 | J24: -12.2 | K24: 424
A25: Other Income | B25: 2622.6 | C25: 2549.8 | D25: 2613.8 | E25: 2727.9 | F25: 2403.7 | G25: 2066.9 | H25: 2274.6 | I25: 2630.8 | J25: 3909.4 | K25: 3899.4
A26: Depreciation | B26: 2310 | C26: 2111.7 | D26: 1946.7 | E26: 2085.5 | F26: 2763.4 | G26: 3077.8 | H26: 3340.2 | I26: 3407.1 | J26: 2957.9 | K26: 2910.7
A27: Interest | B27: 594.2 | C27: 583 | D27: 737.5 | E27: 732.8 | F27: 508.8 | G27: 532.5 | H27: 1007.7 | I27: 1255.2 | J27: 1477 | K27: 1457.7
A28: Profit before tax | B28: 11039.3 | C28: 10242.2 | D28: 11542.2 | E28: 12251.9 | F28: 13902.9 | G28: 15140.8 | H28: 14765.7 | I28: 14721 | J28: 17495.7 | K28: 17342.2
A29: Tax | B29: 2521.4 | C29: 2239.1 | D29: 2524.3 | E29: 2480.1 | F29: 3034.9 | G29: 2897.4 | H29: 3399.2 | I29: 3608.9 | J29: 4277.7 | K29: 4076.7
A30: Net profit | B30: 8493.1 | C30: 8002.8 | D30: 9003.7 | E30: 9722.3 | F30: 10796.4 | G30: 12229.6 | H30: 11350 | I30: 11045.2 | J30: 13135.4 | K30: 13197.4
A31: Dividend Amount | B31: 486.1 | C31: 452.4 | D31: 603.4 | E31: 571.35 | F31: 547.9 | G31: 3289.2 | H31: 548.8 | I31: 522.5 | J31: 6283.2 | K31: 11537.35
A32: EPS | B32: 6.5508916 | C32: 6.6338956 | D32: 7.4608673 | E32: 8.5084058 | F32: 9.8522581 | G32: 11.154222 | H32: 10.340932 | I32: 10.569266 | J32: 12.543234 | K32: 12.582853
A40: Quarters
A41: Report Date | B41: 45291 | C41: 45382 | D41: 45473 | E41: 45565 | F41: 45657 | G41: 45747 | H41: 45838 | I41: 45930 | J41: 46022 | K41: 46112
A42: Sales | B42: 22205.1 | C42: 22208.3 | D42: 21963.8 | E42: 22301.6 | F42: 22318.8 | G42: 22504.2 | H42: 22134.6 | I42: 22697.3 | J42: 23555.8 | K42: 24236.3
A43: Expenses | B43: 18006.8 | C43: 17827.7 | D43: 17614.2 | E43: 17798.3 | F43: 17779 | G43: 17880.2 | H43: 17901.5 | I43: 18324.9 | J43: 19259.4 | K43: 19327
A44: Other Income | B44: 597.9 | C44: 652.9 | D44: 729.7 | E44: 962.2 | F44: 1004.6 | G44: 1217.4 | H44: 1071.5 | I44: 962.9 | J44: 1008.1 | K44: 856.9
A45: Depreciation | B45: 931.6 | C45: 840.5 | D45: 728.9 | E45: 830.8 | F45: 676.5 | G45: 721.7 | H45: 685.5 | I45: 691.7 | J45: 805 | K45: 728.5
A46: Interest | B46: 312.5 | C46: 330.8 | D46: 328.8 | E46: 356.9 | F46: 414.6 | G46: 376.7 | H46: 360.8 | I46: 361.2 | J46: 365.6 | K46: 370.1
A47: Profit before tax | B47: 3552.1 | C47: 3862.2 | D47: 4021.6 | E47: 4277.8 | F47: 4453.3 | G47: 4743 | H47: 4258.3 | I47: 4282.4 | J47: 4133.9 | K47: 4667.6
A48: Tax | B48: 851.5 | C48: 1004 | D48: 985 | E48: 1051.2 | F48: 1086.6 | G48: 1154.9 | H48: 921.8 | I48: 1020 | J48: 988.9 | K48: 1146
A49: Net profit | B49: 2694.2 | C49: 2834.6 | D49: 3003.2 | E49: 3208.8 | F49: 3353.8 | G49: 3569.6 | H49: 3330.4 | I49: 3246.2 | J49: 3119 | K49: 3501.8
A50: Operating Profit | B50: 4198.3 | C50: 4380.6 | D50: 4349.6 | E50: 4503.3 | F50: 4539.8 | G50: 4624 | H50: 4233.1 | I50: 4372.4 | J50: 4296.4 | K50: 4909.3
A55: BALANCE SHEET
A56: Report Date | B56: 42825 | C56: 43190 | D56: 43555 | E56: 43921 | F56: 44286 | G56: 44651 | H56: 45016 | I56: 45382 | J56: 45747 | K56: 46112
A57: Equity Share Capital | B57: 486.1 | C57: 904.8 | D57: 1206.8 | E57: 1142.7 | F57: 1095.8 | G57: 1096.4 | H57: 1097.6 | I57: 1045 | J57: 2094.4 | K57: 2097.7
A58: Reserves | B58: 51184.1 | C58: 47021.5 | D58: 55215.8 | E58: 54179 | F58: 53805.2 | G58: 64306.6 | H58: 76570.3 | I58: 73488 | J58: 80269.7 | K58: 85920.6
A59: Borrowings | B59: 14241.2 | C59: 13901.2 | D59: 9946.7 | E59: 9724 | F59: 10451.4 | G59: 17592.9 | H59: 17466.6 | I59: 16464.9 | J59: 19203.5 | K59: 20291
A60: Other Liabilities | B60: 12760.8 | C60: 13563.3 | D60: 16217.1 | E60: 15953.9 | F60: 17213.4 | G60: 24279.7 | H60: 21789.2 | I60: 23611 | J60: 26361.5 | K60: 32574.2
A61: Total | B61: 78672.2 | C61: 75390.8 | D61: 82586.4 | E61: 80999.6 | F61: 82565.8 | G61: 107275.6 | H61: 116923.7 | I61: 114608.9 | J61: 127929.1 | K61: 140883.5
A62: Net Block | B62: 19886.5 | C62: 18126.7 | D62: 17464.7 | E62: 22062.1 | F62: 23040.3 | G62: 37989.6 | H62: 44756.8 | I62: 43628 | J62: 45186.7 | K62: 51690.1
A63: Capital Work in Progress | B63: 737.7 | C63: 1377.7 | D63: 2141.8 | E63: 1881.1 | F63: 1853.2 | G63: 1601.5 | H63: 617.1 | I63: 723.4 | J63: 196.4 | K63: 412.2
A64: Investments | B64: 29913.3 | C64: 25796.8 | D64: 22886.7 | E64: 20032 | F64: 18774.7 | G64: 26153.8 | H64: 33073.2 | I64: 33384.4 | J64: 43925.9 | K64: 46785.9
A65: Other Assets | B65: 28134.7 | C65: 30089.6 | D65: 40093.2 | E65: 37024.4 | F65: 38897.6 | G65: 41530.7 | H65: 38476.6 | I65: 36873.1 | J65: 38620.1 | K65: 41995.3
A66: Total | B66: 78672.2 | C66: 75390.8 | D66: 82586.4 | E66: 80999.6 | F66: 82565.8 | G66: 107275.6 | H66: 116923.7 | I66: 114608.9 | J66: 127929.1 | K66: 140883.5
A67: Receivables | B67: 9484.6 | C67: 10099 | D67: 10048.9 | E67: 10447.4 | F67: 9429.8 | G67: 11521.9 | H67: 12635 | I67: 11547.7 | J67: 11774.5 | K67: 13590.1
... A70: No. of Equity Shares | B70: 2430900565 | C70: 4523784491 | D70: 6033935388 | E70: 5713357390 | F70: 5479138555 | G70: 5482070115 | H70: 5487917741 | I70: 5225138246 | J70: 10472136049 | K70: 10488412458
A71: New Bonus Shares | C71: 2433074327 | D71: 1508469180
A72: Face value | B72: 2 | C72: 2 | D72: 2 | E72: 2 | F72: 2 | G72: 2 | H72: 2 | I72: 2 | J72: 2 | K72: 2
A73: Return on Equity | B73: 0.16437134 | C73: 0.16698139 | D73: 0.15957613 | E73: 0.17574116 | F73: 0.19665216 | G73: 0.18698836 | H73: 0.14613502 | I73: 0.14819208 | J73: 0.15947968 | K73: 0.14993927
A74: Return on Capital Emp | C74: 0.16948948 | D74: 0.19157576 | E74: 0.19761367 | F74: 0.22104156 | G74: 0.21130407 | H74: 0.17709947 | I74: 0.1716649 | J74: 0.19705191 | K74: 0.17915168
A80: CASH FLOW:
A81: Report Date | B81: 42825 | C81: 43190 | D81: 43555 | E81: 43921 | F81: 44286 | G81: 44651 | H81: 45016 | I81: 45382 | J81: 45747 | K81: 46112
A82: Cash from Operating Activity | B82: 9277.3 | C82: 8423.3 | D82: 11631.6 | E82: 10064.3 | F82: 14755 | G82: 11079.7 | H82: 13060.1 | I82: 17621.6 | J82: 16942.6 | K82: 14931.6
A83: Cash from Investing Activity | B83: -11769.5 | C83: 3595.3 | D83: 5065.2 | E83: 3593.4 | F83: 684.9 | G83: -22321.3 | H83: -8169.2 | I83: 1144.1 | J83: -8044 | K83: -2447.5
A84: Cash from Financing Activity | B84: -2275.2 | C84: -12997.8 | D84: -4936.9 | E84: -15099.8 | F84: -12884 | G84: 4658.6 | H84: -6088.1 | I84: -18256.7 | J84: -6396.3 | K84: -14126
A85: Net Cash Flow | B85: -4767.4 | C85: -979.2 | D85: 11759.9 | E85: -1442.1 | F85: 2555.9 | G85: -6583 | H85: -1197.2 | I85: 509 | J85: 2502.3 | K85: -1641.9
A90: PRICE: | B90: 96.7 | C90: 105.44 | D90: 127.4 | E90: 98.35 | F90: 207.08 | G90: 295.95 | H90: 182.63 | I90: 240.05 | J90: 262.25 | K90: 187.64
A92: DERIVED:
A93: Adjusted Equity Shares in Cr | B93: 1296.48 | C93: 1206.35 | D93: 1206.79 | E93: 1142.67 | F93: 1095.83 | G93: 1096.41 | H93: 1097.58 | I93: 1045.03 | J93: 1047.21 | K93: 1048.84

Sheet TechM
A1: COMPANY NAME | B1: TECH MAHINDRA LTD | E1: =IF(B2<>B3, "A NEW VERSION OF THE WORKSHEET IS AVAILABLE", "")
A2: LATEST VERSION | B2: 2.1 | E2: PLEASE DO NOT MAKE ANY CHANGES TO THIS SHEET
A3: CURRENT VERSION | B3: 2.1
A5: META
A6: Number of shares | B6: =IF(B9>0, B9/B8, 0) -> 98.005794
A7: Face Value | B7: 5
A8: Current Price | B8: 1410.1
A9: Market Capitalization | B9: 138197.97
A15: PROFIT & LOSS
A16: Report Date | B16: 42825 | C16: 43190 | D16: 43555 | E16: 43921 | F16: 44286 | G16: 44651 | H16: 45016 | I16: 45382 | J16: 45747 | K16: 46112
A17: Sales | B17: 29140.8 | C17: 30772.9 | D17: 34742.1 | E17: 36867.7 | F17: 37855.1 | G17: 44646 | H17: 53290.2 | I17: 51995.5 | J17: 52988.3 | K17: 56815.4
A18: Raw Material Cost
A19: Change in Inventory
A20: Power and Fuel | B20: 187.9 | C20: 194.7 | D20: 199.2 | E20: 205.3 | F20: 140.4 | G20: 139.9 | H20: 175.3 | I20: 194.7 | J20: 192.2 | K20: 205.7
A21: Other Mfr. Exp | B21: 5910.3 | C21: 5861.6 | D21: 6716.7 | E21: 8293.7 | F21: 8564.1 | G21: 11289.8 | H21: 13628.8 | I21: 12770.6 | J21: 12213.3 | K21: 13388.1
A22: Employee Cost | B22: 15453.9 | C22: 16624 | D22: 17507.9 | E22: 18810 | F22: 19297.3 | G22: 22285.9 | H22: 27691.8 | I22: 29128.3 | J22: 29623.8 | K22: 30478.8
A23: Selling and admin | B23: 3053.2 | C23: 3008.1 | D23: 3422.1 | E23: 3400.1 | F23: 2316 | G23: 2592.2 | H23: 3011.1 | I23: 3284.1 | J23: 3248.9 | K23: 3261.9
A24: Other Expenses | B24: 351.1 | C24: 374.9 | D24: 624.8 | E24: 655.5 | F24: 741 | G24: 318.2 | H24: 1020.4 | I24: 2111.5 | J24: 746.3 | K24: 448.3
A25: Other Income | B25: 775.3 | C25: 1416.6 | D25: 534.2 | E25: 1192.4 | F25: 788.3 | G25: 1115.1 | H25: 965 | I25: 927.4 | J25: 864 | K25: -240.5
A26: Depreciation | B26: 978.1 | C26: 1085 | D26: 1129.2 | E26: 1445.8 | F26: 1457.7 | G26: 1520.4 | H26: 1956.7 | I26: 1817.1 | J26: 1852.9 | K26: 1881.6
A27: Interest | B27: 128.6 | C27: 162.4 | D27: 133.2 | E27: 191.9 | F27: 174 | G27: 162.6 | H27: 325.6 | I27: 392.2 | J27: 321.7 | K27: 337.4
A28: Profit before tax | B28: 3853 | C28: 4878.8 | D28: 5543.2 | E28: 5057.8 | F28: 5952.9 | G28: 7452.1 | H28: 6445.5 | I28: 3224.4 | J28: 5653.2 | K28: 6573.1
A29: Tax | B29: 1002.1 | C29: 1092.6 | D29: 1254.4 | E29: 1160.4 | F29: 1599.9 | G29: 1822 | H29: 1588.5 | I29: 827.6 | J29: 1400.2 | K29: 1767.6
A30: Net profit | B30: 2812.9 | C30: 3799.8 | D30: 4297.6 | E30: 4033 | F30: 4428 | G30: 5566.1 | H30: 4831.3 | I30: 2357.8 | J30: 4251.5 | K30: 4810.9
A31: Dividend Amount | B31: 789.84 | C31: 1236.76 | D31: 1242.36 | E31: 1307.7 | F31: 3933 | G31: 2632.8 | H31: 4400 | I31: 3530.4 | J31: 3981.6 | K31: 4516.56
A32: EPS | B32: 28.876912 | C32: 38.785342 | D32: 43.701444 | E32: 41.753805 | F32: 45.729629 | G32: 57.276189 | H32: 49.597577 | I32: 24.138002 | J32: 43.426966 | K32: 49.100837
A40: Quarters
A41: Report Date | B41: 45291 | C41: 45382 | D41: 45473 | E41: 45565 | F41: 45657 | G41: 45747 | H41: 45838 | I41: 45930 | J41: 46022 | K41: 46112
A42: Sales | B42: 13101.3 | C42: 12871.3 | D42: 13005.5 | E42: 13313.2 | F42: 13285.6 | G42: 13384 | H42: 13351.2 | I42: 13994.9 | J42: 14393.2 | K42: 15076.1
A43: Expenses | B43: 11954.9 | C43: 11772.2 | D43: 11441 | E43: 11563 | F43: 11476.6 | G43: 11545.1 | H43: 11416 | I43: 11829.7 | J43: 12027.6 | K43: 12510.9
A44: Other Income | B44: 92.3 | C44: 379.9 | D44: 147.3 | E44: 522.1 | F44: 23.1 | G44: 172.7 | H44: 218.8 | I44: 40 | J44: -293.2 | K44: -204.7
A45: Depreciation | B45: 443.4 | C45: 461.4 | D45: 462.2 | E45: 469.8 | F45: 458.8 | G45: 462.1 | H45: 458.1 | I45: 468.7 | J45: 473.7 | K45: 481.1
A46: Interest | B46: 116.5 | C46: 58.5 | D46: 71.5 | E46: 89 | F46: 75.9 | G46: 85.3 | H46: 77.8 | I46: 77.2 | J46: 93.6 | K46: 88.8
A47: Profit before tax | B47: 678.8 | C47: 959.1 | D47: 1178.1 | E47: 1713.5 | F47: 1297.4 | G47: 1464.2 | H47: 1618.1 | I47: 1659.3 | J47: 1505.1 | K47: 1790.6
A48: Tax | B48: 155.1 | C48: 294.9 | D48: 313.3 | E48: 456 | F48: 308.6 | G48: 322.3 | H48: 489.3 | I48: 457.6 | J48: 386.5 | K48: 434.2
A49: Net profit | B49: 510.4 | C49: 661 | D49: 851.5 | E49: 1250.1 | F49: 983.2 | G49: 1166.7 | H49: 1140.6 | I49: 1194.5 | J49: 1122 | K49: 1353.8
A50: Operating Profit | B50: 1146.4 | C50: 1099.1 | D50: 1564.5 | E50: 1750.2 | F50: 1809 | G50: 1838.9 | H50: 1935.2 | I50: 2165.2 | J50: 2365.6 | K50: 2565.2
A55: BALANCE SHEET
A56: Report Date | B56: 42825 | C56: 43190 | D56: 43555 | E56: 43921 | F56: 44286 | G56: 44651 | H56: 45016 | I56: 45382 | J56: 45747 | K56: 46112
A57: Equity Share Capital | B57: 438.8 | C57: 441.7 | D57: 443.7 | E57: 435.9 | F57: 437 | G57: 438.8 | H57: 440 | I57: 441.3 | J57: 442.4 | K57: 442.8
A58: Reserves | B58: 15998.4 | C58: 18401.1 | D58: 19840.7 | E58: 21377.2 | F58: 24428 | G58: 26446.9 | H58: 27484.5 | I58: 26228.1 | J58: 26919.1 | K58: 29172.6
A59: Borrowings | B59: 1366.2 | C59: 2396.6 | D59: 1995.5 | E59: 3670.5 | F59: 2900.8 | G59: 2618.4 | H59: 2740.2 | I59: 2536.7 | J59: 2025.2 | K59: 2186.2
A60: Other Liabilities | B60: 8253.6 | C60: 9192 | D60: 11165.9 | E60: 11834.3 | F60: 11836.1 | G60: 14911.4 | H60: 15162.5 | I60: 13943 | J60: 14879.9 | K60: 17366.1
A61: Total | B61: 26057 | C61: 30431.4 | D61: 33445.8 | E61: 37317.9 | F61: 39601.9 | G61: 44415.5 | H61: 45827.2 | I61: 43149.1 | J61: 44266.6 | K61: 49167.7
A62: Net Block | B62: 6460.1 | C62: 7622.4 | D62: 7061.2 | E62: 8872 | F62: 9018.5 | G62: 14783.6 | H62: 14931.5 | I62: 13903 | J62: 13981.5 | K62: 14864
A63: Capital Work in Progress | B63: 372.9 | C63: 239.9 | D63: 276.3 | E63: 50.1 | F63: 118.3 | G63: 165.1 | H63: 119.7 | I63: 133.2 | J63: 20.6 | K63: 26.8
A64: Investments | B64: 2395.5 | C64: 4840.7 | D64: 7341.9 | E64: 5848.3 | F64: 10237.6 | G64: 4883.8 | H64: 3388.1 | I64: 3237.7 | J64: 3182.1 | K64: 3425.7
A65: Other Assets | B65: 16828.5 | C65: 17728.4 | D65: 18766.4 | E65: 22547.5 | F65: 20227.5 | G65: 24583 | H65: 27387.9 | I65: 25875.2 | J65: 27082.4 | K65: 30851.2
A66: Total | B66: 26057 | C66: 30431.4 | D66: 33445.8 | E66: 37317.9 | F66: 39601.9 | G66: 44415.5 | H66: 45827.2 | I66: 43149.1 | J66: 44266.6 | K66: 49167.7
A67: Receivables | B67: 5337.7 | C67: 6497.9 | D67: 6958.6 | E67: 7577.2 | F67: 6472.8 | G67: 11933.4 | H67: 12881.6 | I67: 11401.1 | J67: 11547 | K67: 13357.7
... A70: No. of Equity Shares | B70: 877539300 | C70: 979733808 | D70: 887268630 | E70: 965852364 | F70: 873959406 | G70: 877597850 | H70: 879911846 | I70: 882522894 | J70: 884758083 | K70: 885605623
A71: New Bonus Shares
A72: Face value | B72: 5 | C72: 5 | D72: 5 | E72: 5 | F72: 5 | G72: 5 | H72: 5 | I72: 5 | J72: 5 | K72: 5
A73: Return on Equity | B73: 0.17113012 | C73: 0.20165793 | D73: 0.21186725 | E73: 0.1848889 | F73: 0.17808164 | G73: 0.20702827 | H73: 0.17301295 | I73: 0.088408438 | J73: 0.15538256 | K73: 0.16244589
A74: Return on Capital Emp | C74: 0.25823968 | D74: 0.26086817 | E74: 0.21982057 | F74: 0.2301209 | G74: 0.26592329 | H74: 0.22507014 | I74: 0.12081349 | J74: 0.20394656 | K74: 0.22587652
A80: CASH FLOW:
A81: Report Date | B81: 42825 | C81: 43190 | D81: 43555 | E81: 43921 | F81: 44286 | G81: 44651 | H81: 45016 | I81: 45382 | J81: 45747 | K81: 46112
A82: Cash from Operating Activity | B82: 4071.4 | C82: 3553.5 | D82: 4432 | E82: 4358.1 | F82: 8093.8 | G82: 5285.3 | H82: 5572 | I82: 6376.4 | J82: 5785.7 | K82: 6172
A83: Cash from Investing Activity | B83: -2893 | C83: -3319.3 | D83: -2104.2 | E83: 1081.4 | F83: -5433.2 | G83: 479.8 | H83: -226.5 | I83: -1318.4 | J83: -15.1 | K83: -313.9
A84: Cash from Financing Activity | B84: -1570.9 | C84: -269.4 | D84: -2251.2 | E84: -4465.5 | F84: -2986.9 | G84: -4666.6 | H84: -5078.1 | I84: -4767.2 | J84: -5799.2 | K84: -5130.5
A85: Net Cash Flow | B85: -392.5 | C85: -35.2 | D85: 76.6 | E85: 974 | F85: -326.3 | G85: 1098.5 | H85: 267.4 | I85: 290.8 | J85: -28.6 | K85: 727.6
A90: PRICE: | B90: 459.15 | C90: 638.7 | D90: 775.9 | E90: 565.5 | F90: 991.45 | G90: 1499.45 | H90: 1101.85 | I90: 1248.1 | J90: 1418.25 | K90: 1384
A92: DERIVED:
A93: Adjusted Equity Shares in Cr | B93: 97.41 | C93: 97.97 | D93: 98.34 | E93: 96.59 | F93: 96.83 | G93: 97.18 | H93: 97.41 | I93: 97.68 | J93: 97.9 | K93: 97.98
